{"variants":[{"traits":[{"interfaceLanguage":"swift"}],"paths":["\/documentation\/dotfacecore"]},{"paths":["\/documentation\/dotfacecore"],"traits":[{"interfaceLanguage":"occ"}]}],"sections":[],"identifier":{"interfaceLanguage":"swift","url":"doc:\/\/DotFaceCore\/documentation\/DotFaceCore"},"kind":"symbol","schemaVersion":{"minor":3,"patch":0,"major":0},"hierarchy":{"paths":[[]]},"abstract":[{"text":"version: 8.6.1","type":"text"}],"topicSections":[{"identifiers":["doc:\/\/DotFaceCore\/documentation\/DotFaceCore\/DotFaceModule","doc:\/\/DotFaceCore\/documentation\/DotFaceCore\/DotFaceModuleId","doc:\/\/DotFaceCore\/documentation\/DotFaceCore\/DotFaceModuleCategory"],"title":"DotFace modularization"},{"title":"Global components","identifiers":["doc:\/\/DotFaceCore\/documentation\/DotFaceCore\/DotFaceLibrary","doc:\/\/DotFaceCore\/documentation\/DotFaceCore\/Logger","doc:\/\/DotFaceCore\/documentation\/DotFaceCore\/Localization"]},{"title":"UI components","identifiers":["doc:\/\/DotFaceCore\/documentation\/DotFaceCore\/FaceAutoCaptureViewController","doc:\/\/DotFaceCore\/documentation\/DotFaceCore\/FaceSimpleCaptureViewController","doc:\/\/DotFaceCore\/documentation\/DotFaceCore\/EyeGazeLivenessViewController","doc:\/\/DotFaceCore\/documentation\/DotFaceCore\/SmileLivenessViewController","doc:\/\/DotFaceCore\/documentation\/DotFaceCore\/MagnifEyeLivenessViewController"]},{"title":"Non-UI components","identifiers":["doc:\/\/DotFaceCore\/documentation\/DotFaceCore\/FaceDetector","doc:\/\/DotFaceCore\/documentation\/DotFaceCore\/FaceMatcher","doc:\/\/DotFaceCore\/documentation\/DotFaceCore\/TemplateMatcher"]},{"title":"Face evaluation","identifiers":["doc:\/\/DotFaceCore\/documentation\/DotFaceCore\/FaceAttribute","doc:\/\/DotFaceCore\/documentation\/DotFaceCore\/FaceAspects","doc:\/\/DotFaceCore\/documentation\/DotFaceCore\/FaceQuality","doc:\/\/DotFaceCore\/documentation\/DotFaceCore\/FaceQualityQuery","doc:\/\/DotFaceCore\/documentation\/DotFaceCore\/FaceImageQuality","doc:\/\/DotFaceCore\/documentation\/DotFaceCore\/FaceImageQualityQuery","doc:\/\/DotFaceCore\/documentation\/DotFaceCore\/HeadPose","doc:\/\/DotFaceCore\/documentation\/DotFaceCore\/HeadPoseAttribute","doc:\/\/DotFaceCore\/documentation\/DotFaceCore\/HeadPoseQuery","doc:\/\/DotFaceCore\/documentation\/DotFaceCore\/Expression","doc:\/\/DotFaceCore\/documentation\/DotFaceCore\/EyesExpression","doc:\/\/DotFaceCore\/documentation\/DotFaceCore\/EyesExpressionQuery","doc:\/\/DotFaceCore\/documentation\/DotFaceCore\/ExpressionQuery","doc:\/\/DotFaceCore\/documentation\/DotFaceCore\/Wearables","doc:\/\/DotFaceCore\/documentation\/DotFaceCore\/WearablesQuery","doc:\/\/DotFaceCore\/documentation\/DotFaceCore\/Glasses"]},{"identifiers":["doc:\/\/DotFaceCore\/documentation\/DotFaceCore\/BgrRawImage","doc:\/\/DotFaceCore\/documentation\/DotFaceCore\/BgrRawImageFactory","doc:\/\/DotFaceCore\/documentation\/DotFaceCore\/CGImageFactory","doc:\/\/DotFaceCore\/documentation\/DotFaceCore\/CIImageFactory"],"title":"Converting images"},{"identifiers":["doc:\/\/DotFaceCore\/documentation\/DotFaceCore\/BgraRawImage","doc:\/\/DotFaceCore\/documentation\/DotFaceCore\/BgraRawImageFactory","doc:\/\/DotFaceCore\/documentation\/DotFaceCore\/Corners","doc:\/\/DotFaceCore\/documentation\/DotFaceCore\/DefaultTimedCaptureEvaluator","doc:\/\/DotFaceCore\/documentation\/DotFaceCore\/DotFaceModuleCategoryWrapper","doc:\/\/DotFaceCore\/documentation\/DotFaceCore\/DotSdk","doc:\/\/DotFaceCore\/documentation\/DotFaceCore\/DotSdkConfiguration","doc:\/\/DotFaceCore\/documentation\/DotFaceCore\/EyeGazeLivenessResult","doc:\/\/DotFaceCore\/documentation\/DotFaceCore\/FaceDetectionQuery","doc:\/\/DotFaceCore\/documentation\/DotFaceCore\/FaceFeaturePoint","doc:\/\/DotFaceCore\/documentation\/DotFaceCore\/FaceFeatureWrapper","doc:\/\/DotFaceCore\/documentation\/DotFaceCore\/ImageSize","doc:\/\/DotFaceCore\/documentation\/DotFaceCore\/InstructionCandidateSelectionStyle","doc:\/\/DotFaceCore\/documentation\/DotFaceCore\/InstructionStyle","doc:\/\/DotFaceCore\/documentation\/DotFaceCore\/IntervalDouble","doc:\/\/DotFaceCore\/documentation\/DotFaceCore\/IntervalFloat","doc:\/\/DotFaceCore\/documentation\/DotFaceCore\/PlaceholderCandidateSelectionStyle","doc:\/\/DotFaceCore\/documentation\/DotFaceCore\/PlaceholderStyle","doc:\/\/DotFaceCore\/documentation\/DotFaceCore\/PointDouble","doc:\/\/DotFaceCore\/documentation\/DotFaceCore\/PreviewViewStyle","doc:\/\/DotFaceCore\/documentation\/DotFaceCore\/RandomEyeGazeLivenessCornersGenerator","doc:\/\/DotFaceCore\/documentation\/DotFaceCore\/RectangleDouble","doc:\/\/DotFaceCore\/documentation\/DotFaceCore\/TiltAngles","doc:\/\/DotFaceCore\/documentation\/DotFaceCore\/ValueRange","doc:\/\/DotFaceCore\/documentation\/DotFaceCore\/WrappedDouble","doc:\/\/DotFaceCore\/documentation\/DotFaceCore\/WrappedEyeGazeLivenessCorner","doc:\/\/DotFaceCore\/documentation\/DotFaceCore\/WrappedFloat"],"title":"Classes"},{"identifiers":["doc:\/\/DotFaceCore\/documentation\/DotFaceCore\/DotLibrary","doc:\/\/DotFaceCore\/documentation\/DotFaceCore\/DotSdkError","doc:\/\/DotFaceCore\/documentation\/DotFaceCore\/DotSdkLicenseProxyProtocol","doc:\/\/DotFaceCore\/documentation\/DotFaceCore\/EyeGazeLivenessCornersGenerator","doc:\/\/DotFaceCore\/documentation\/DotFaceCore\/TimedCaptureEvaluator"],"title":"Protocols"},{"title":"Enumerations","identifiers":["doc:\/\/DotFaceCore\/documentation\/DotFaceCore\/CameraFacing","doc:\/\/DotFaceCore\/documentation\/DotFaceCore\/CameraPreviewScaleType","doc:\/\/DotFaceCore\/documentation\/DotFaceCore\/CaptureMode","doc:\/\/DotFaceCore\/documentation\/DotFaceCore\/DotLibraryId","doc:\/\/DotFaceCore\/documentation\/DotFaceCore\/EyeGazeLivenessCorner","doc:\/\/DotFaceCore\/documentation\/DotFaceCore\/FaceFeature","doc:\/\/DotFaceCore\/documentation\/DotFaceCore\/LoggerLogLevel"]}],"primaryContentSections":[{"content":[{"text":"Overview","level":2,"type":"heading","anchor":"overview"},{"type":"paragraph","inlineContent":[{"type":"text","text":"DotFaceCore is a part of DotFace framework group which provides components for the digital onboarding process using the latest Innovatrics IFace image processing library. It wraps the core functionality of IFace library to a higher-level module which is easy to integrate into an iOS application."}]}],"kind":"content"}],"metadata":{"title":"DotFaceCore","role":"collection","roleHeading":"Framework","modules":[{"name":"DotFaceCore"}],"externalID":"DotFaceCore","symbolKind":"module"},"references":{"doc://DotFaceCore/documentation/DotFaceCore/DotFaceModuleCategory":{"fragments":[{"kind":"keyword","text":"enum"},{"kind":"text","text":" "},{"text":"DotFaceModuleCategory","kind":"identifier"}],"url":"\/documentation\/dotfacecore\/dotfacemodulecategory","abstract":[{"code":"DotFace","type":"codeVoice"},{"type":"text","text":" module category."}],"kind":"symbol","navigatorTitle":[{"text":"DotFaceModuleCategory","kind":"identifier"}],"type":"topic","role":"symbol","identifier":"doc:\/\/DotFaceCore\/documentation\/DotFaceCore\/DotFaceModuleCategory","title":"DotFaceModuleCategory"},"doc://DotFaceCore/documentation/DotFaceCore/DOTFEyeGazeLivenessConfiguration":{"title":"DOTFEyeGazeLivenessConfiguration","kind":"symbol","abstract":[{"text":"Configuration options for the eye gaze liveness process.","type":"text"}],"type":"topic","identifier":"doc:\/\/DotFaceCore\/documentation\/DotFaceCore\/DOTFEyeGazeLivenessConfiguration","url":"\/documentation\/dotfacecore\/dotfeyegazelivenessconfiguration","role":"symbol","fragments":[{"kind":"identifier","text":"DOTFEyeGazeLivenessConfiguration"}]},"doc://DotFaceCore/documentation/DotFaceCore/DOTFFaceAutoCaptureConfiguration":{"fragments":[{"kind":"identifier","text":"DOTFFaceAutoCaptureConfiguration"}],"identifier":"doc:\/\/DotFaceCore\/documentation\/DotFaceCore\/DOTFFaceAutoCaptureConfiguration","kind":"symbol","title":"DOTFFaceAutoCaptureConfiguration","type":"topic","url":"\/documentation\/dotfacecore\/dotffaceautocaptureconfiguration","abstract":[{"type":"text","text":"Configuration options for the face auto capture process."}],"role":"symbol"},"https://developer.apple.com/documentation/coremotion/getting_raw_accelerometer_events":{"identifier":"https:\/\/developer.apple.com\/documentation\/coremotion\/getting_raw_accelerometer_events","titleInlineContent":[{"type":"text","text":"Sensor Coordinate System"}],"url":"https:\/\/developer.apple.com\/documentation\/coremotion\/getting_raw_accelerometer_events","type":"link","title":"Sensor Coordinate System"},"doc://DotFaceCore/documentation/DotFaceCore/PointDouble":{"title":"PointDouble","identifier":"doc:\/\/DotFaceCore\/documentation\/DotFaceCore\/PointDouble","url":"\/documentation\/dotfacecore\/pointdouble","type":"topic","kind":"symbol","role":"symbol","navigatorTitle":[{"kind":"identifier","text":"PointDouble"}],"abstract":[{"type":"text","text":"Two dimensional point with "},{"type":"codeVoice","code":"Double"},{"type":"text","text":" value type."}],"fragments":[{"kind":"keyword","text":"class"},{"kind":"text","text":" "},{"kind":"identifier","text":"PointDouble"}]},"doc://DotFaceCore/documentation/DotFaceCore":{"title":"DotFaceCore","kind":"symbol","abstract":[{"text":"version: 8.6.1","type":"text"}],"type":"topic","identifier":"doc:\/\/DotFaceCore\/documentation\/DotFaceCore","url":"\/documentation\/dotfacecore","role":"collection"},"doc://DotFaceCore/documentation/DotFaceCore/DOTFFaceSimpleCaptureConfiguration":{"role":"symbol","kind":"symbol","fragments":[{"kind":"identifier","text":"DOTFFaceSimpleCaptureConfiguration"}],"url":"\/documentation\/dotfacecore\/dotffacesimplecaptureconfiguration","abstract":[{"type":"text","text":"Configuration options for the face simple capture process."}],"title":"DOTFFaceSimpleCaptureConfiguration","type":"topic","identifier":"doc:\/\/DotFaceCore\/documentation\/DotFaceCore\/DOTFFaceSimpleCaptureConfiguration"},"doc://DotFaceCore/documentation/DotFaceCore/DotCameraVersionNumber":{"role":"symbol","type":"topic","fragments":[{"text":"DotCameraVersionNumber","kind":"identifier"}],"identifier":"doc:\/\/DotFaceCore\/documentation\/DotFaceCore\/DotCameraVersionNumber","abstract":[{"type":"text","text":"Project version number for DotCamera."}],"kind":"symbol","title":"DotCameraVersionNumber","url":"\/documentation\/dotfacecore\/dotcameraversionnumber"},"doc://DotFaceCore/documentation/DotFaceCore/FaceAttribute":{"abstract":[{"text":"The evaluation result of a single face quality attribute, for example sharpness or passive liveness.","type":"text"}],"fragments":[{"text":"class","kind":"keyword"},{"text":" ","kind":"text"},{"text":"FaceAttribute","kind":"identifier"}],"navigatorTitle":[{"text":"FaceAttribute","kind":"identifier"}],"role":"symbol","url":"\/documentation\/dotfacecore\/faceattribute","kind":"symbol","type":"topic","title":"FaceAttribute","identifier":"doc:\/\/DotFaceCore\/documentation\/DotFaceCore\/FaceAttribute"},"doc://DotFaceCore/documentation/DotFaceCore/DOTFFaceMatcherResult":{"url":"\/documentation\/dotfacecore\/dotffacematcherresult","abstract":[{"text":"Face matcher result.","type":"text"}],"role":"symbol","identifier":"doc:\/\/DotFaceCore\/documentation\/DotFaceCore\/DOTFFaceMatcherResult","title":"DOTFFaceMatcherResult","fragments":[{"text":"DOTFFaceMatcherResult","kind":"identifier"}],"kind":"symbol","type":"topic"},"doc://DotFaceCore/documentation/DotFaceCore/FaceImageQuality":{"identifier":"doc:\/\/DotFaceCore\/documentation\/DotFaceCore\/FaceImageQuality","kind":"symbol","type":"topic","role":"symbol","navigatorTitle":[{"kind":"identifier","text":"FaceImageQuality"}],"title":"FaceImageQuality","url":"\/documentation\/dotfacecore\/faceimagequality","abstract":[{"type":"text","text":"Face image quality evaluation result. Contains all the evaluated face attributes which together represent the face image quality."}],"fragments":[{"kind":"keyword","text":"class"},{"text":" ","kind":"text"},{"kind":"identifier","text":"FaceImageQuality"}]},"doc://DotFaceCore/documentation/DotFaceCore/ImageSize":{"type":"topic","kind":"symbol","title":"ImageSize","navigatorTitle":[{"text":"ImageSize","kind":"identifier"}],"url":"\/documentation\/dotfacecore\/imagesize","fragments":[{"text":"class","kind":"keyword"},{"text":" ","kind":"text"},{"kind":"identifier","text":"ImageSize"}],"abstract":[{"text":"Image size in pixels.","type":"text"}],"role":"symbol","identifier":"doc:\/\/DotFaceCore\/documentation\/DotFaceCore\/ImageSize"},"doc://DotFaceCore/documentation/DotFaceCore/Expression":{"identifier":"doc:\/\/DotFaceCore\/documentation\/DotFaceCore\/Expression","kind":"symbol","type":"topic","role":"symbol","navigatorTitle":[{"kind":"identifier","text":"Expression"}],"title":"Expression","url":"\/documentation\/dotfacecore\/expression","abstract":[{"type":"text","text":"Face expression evaluation result. Contains evaluated face attributes which represent the face expression."}],"fragments":[{"kind":"keyword","text":"class"},{"kind":"text","text":" "},{"kind":"identifier","text":"Expression"}]},"doc://DotFaceCore/documentation/DotFaceCore/Glasses":{"fragments":[{"kind":"keyword","text":"class"},{"text":" ","kind":"text"},{"kind":"identifier","text":"Glasses"}],"navigatorTitle":[{"kind":"identifier","text":"Glasses"}],"url":"\/documentation\/dotfacecore\/glasses","type":"topic","role":"symbol","kind":"symbol","identifier":"doc:\/\/DotFaceCore\/documentation\/DotFaceCore\/Glasses","title":"Glasses","abstract":[{"type":"text","text":"Face attribute for the glasses."}]},"doc://DotFaceCore/documentation/DotFaceCore/DotSdkError":{"fragments":[{"text":"protocol","kind":"keyword"},{"kind":"text","text":" "},{"text":"DotSdkError","kind":"identifier"}],"kind":"symbol","role":"symbol","url":"\/documentation\/dotfacecore\/dotsdkerror","identifier":"doc:\/\/DotFaceCore\/documentation\/DotFaceCore\/DotSdkError","navigatorTitle":[{"kind":"identifier","text":"DotSdkError"}],"title":"DotSdkError","abstract":[],"type":"topic"},"doc://DotFaceCore/documentation/DotFaceCore/DOTFFaceAutoCaptureStyle":{"abstract":[{"type":"text","text":"Customization options for the face auto capture user interface."}],"url":"\/documentation\/dotfacecore\/dotffaceautocapturestyle","kind":"symbol","role":"symbol","type":"topic","identifier":"doc:\/\/DotFaceCore\/documentation\/DotFaceCore\/DOTFFaceAutoCaptureStyle","title":"DOTFFaceAutoCaptureStyle","fragments":[{"kind":"identifier","text":"DOTFFaceAutoCaptureStyle"}]},"doc://DotFaceCore/documentation/DotFaceCore/DotFaceModuleCategoryWrapper":{"navigatorTitle":[{"kind":"identifier","text":"DotFaceModuleCategoryWrapper"}],"abstract":[{"type":"text","text":"Wrapped "},{"code":"DotFaceModuleCategory","type":"codeVoice"},{"text":" value for Objective-C support.","type":"text"}],"identifier":"doc:\/\/DotFaceCore\/documentation\/DotFaceCore\/DotFaceModuleCategoryWrapper","kind":"symbol","type":"topic","url":"\/documentation\/dotfacecore\/dotfacemodulecategorywrapper","role":"symbol","fragments":[{"kind":"keyword","text":"class"},{"text":" ","kind":"text"},{"text":"DotFaceModuleCategoryWrapper","kind":"identifier"}],"title":"DotFaceModuleCategoryWrapper"},"doc://DotFaceCore/documentation/DotFaceCore/IntervalDouble":{"navigatorTitle":[{"text":"IntervalDouble","kind":"identifier"}],"abstract":[{"text":"Representation of closed interval with value type ","type":"text"},{"type":"codeVoice","code":"Double"},{"text":".","type":"text"},{"text":" ","type":"text"},{"type":"text","text":"The "},{"code":"max","type":"codeVoice"},{"text":" must be greater than the ","type":"text"},{"code":"min","type":"codeVoice"},{"text":".","type":"text"}],"title":"IntervalDouble","identifier":"doc:\/\/DotFaceCore\/documentation\/DotFaceCore\/IntervalDouble","type":"topic","url":"\/documentation\/dotfacecore\/intervaldouble","fragments":[{"text":"class","kind":"keyword"},{"kind":"text","text":" "},{"text":"IntervalDouble","kind":"identifier"}],"role":"symbol","kind":"symbol"},"doc://DotFaceCore/documentation/DotFaceCore/DOTFMagnifEyeLivenessConfiguration":{"identifier":"doc:\/\/DotFaceCore\/documentation\/DotFaceCore\/DOTFMagnifEyeLivenessConfiguration","title":"DOTFMagnifEyeLivenessConfiguration","kind":"symbol","role":"symbol","abstract":[{"text":"Configuration options for the MagnifEye liveness process.","type":"text"}],"fragments":[{"text":"DOTFMagnifEyeLivenessConfiguration","kind":"identifier"}],"url":"\/documentation\/dotfacecore\/dotfmagnifeyelivenessconfiguration","type":"topic"},"doc://DotFaceCore/documentation/DotFaceCore/Wearables":{"fragments":[{"kind":"keyword","text":"class"},{"kind":"text","text":" "},{"text":"Wearables","kind":"identifier"}],"navigatorTitle":[{"kind":"identifier","text":"Wearables"}],"url":"\/documentation\/dotfacecore\/wearables","type":"topic","role":"symbol","kind":"symbol","abstract":[{"type":"text","text":"Wearables evaluation result. Contains evaluated face attributes which represent the detected face wearables."}],"title":"Wearables","identifier":"doc:\/\/DotFaceCore\/documentation\/DotFaceCore\/Wearables"},"doc://DotFaceCore/documentation/DotFaceCore/Logger":{"title":"Logger","identifier":"doc:\/\/DotFaceCore\/documentation\/DotFaceCore\/Logger","type":"topic","fragments":[{"text":"class","kind":"keyword"},{"kind":"text","text":" "},{"text":"Logger","kind":"identifier"}],"navigatorTitle":[{"text":"Logger","kind":"identifier"}],"abstract":[{"type":"text","text":"Static class responsible for generating logs. You can configure log level."}],"role":"symbol","kind":"symbol","url":"\/documentation\/dotfacecore\/logger"},"doc://DotFaceCore/documentation/DotFaceCore/FaceQualityQuery":{"abstract":[{"type":"text","text":"Face quality query specifies which face quality face attributes should be evaluated."}],"kind":"symbol","navigatorTitle":[{"kind":"identifier","text":"FaceQualityQuery"}],"fragments":[{"kind":"keyword","text":"class"},{"text":" ","kind":"text"},{"kind":"identifier","text":"FaceQualityQuery"}],"type":"topic","title":"FaceQualityQuery","url":"\/documentation\/dotfacecore\/facequalityquery","identifier":"doc:\/\/DotFaceCore\/documentation\/DotFaceCore\/FaceQualityQuery","role":"symbol"},"doc://DotFaceCore/documentation/DotFaceCore/CameraFacing":{"role":"symbol","title":"CameraFacing","abstract":[{"text":"Facing of the camera on the device.","type":"text"}],"type":"topic","kind":"symbol","navigatorTitle":[{"kind":"identifier","text":"CameraFacing"}],"fragments":[{"text":"enum","kind":"keyword"},{"kind":"text","text":" "},{"text":"CameraFacing","kind":"identifier"}],"identifier":"doc:\/\/DotFaceCore\/documentation\/DotFaceCore\/CameraFacing","url":"\/documentation\/dotfacecore\/camerafacing"},"doc://DotFaceCore/documentation/DotFaceCore/DotCameraVersionString":{"url":"\/documentation\/dotfacecore\/dotcameraversionstring","identifier":"doc:\/\/DotFaceCore\/documentation\/DotFaceCore\/DotCameraVersionString","role":"symbol","type":"topic","abstract":[{"type":"text","text":"Project version string for DotCamera."}],"title":"DotCameraVersionString","kind":"symbol","fragments":[{"kind":"identifier","text":"DotCameraVersionString"}]},"doc://DotFaceCore/documentation/DotFaceCore/Corners":{"title":"Corners","identifier":"doc:\/\/DotFaceCore\/documentation\/DotFaceCore\/Corners","url":"\/documentation\/dotfacecore\/corners","type":"topic","kind":"symbol","role":"symbol","navigatorTitle":[{"text":"Corners","kind":"identifier"}],"abstract":[{"type":"text","text":"Four detected corners in an image."}],"fragments":[{"kind":"keyword","text":"class"},{"kind":"text","text":" "},{"kind":"identifier","text":"Corners"}]},"doc://DotFaceCore/documentation/DotFaceCore/ValueRange":{"navigatorTitle":[{"kind":"identifier","text":"ValueRange"}],"title":"ValueRange","kind":"symbol","abstract":[{"type":"text","text":"Representation of "},{"type":"codeVoice","code":"Double"},{"type":"text","text":" range, compatible with Objective-C."},{"type":"text","text":" "},{"type":"text","text":"The "},{"type":"codeVoice","code":"max"},{"text":" must be greater than ","type":"text"},{"code":"min","type":"codeVoice"},{"type":"text","text":"."}],"type":"topic","identifier":"doc:\/\/DotFaceCore\/documentation\/DotFaceCore\/ValueRange","url":"\/documentation\/dotfacecore\/valuerange","role":"symbol","fragments":[{"text":"class","kind":"keyword"},{"kind":"text","text":" "},{"text":"ValueRange","kind":"identifier"}]},"doc://DotFaceCore/documentation/DotFaceCore/DefaultTimedCaptureEvaluator":{"kind":"symbol","identifier":"doc:\/\/DotFaceCore\/documentation\/DotFaceCore\/DefaultTimedCaptureEvaluator","title":"DefaultTimedCaptureEvaluator","abstract":[],"navigatorTitle":[{"text":"DefaultTimedCaptureEvaluator","kind":"identifier"}],"type":"topic","role":"symbol","url":"\/documentation\/dotfacecore\/defaulttimedcaptureevaluator","fragments":[{"text":"class","kind":"keyword"},{"text":" ","kind":"text"},{"kind":"identifier","text":"DefaultTimedCaptureEvaluator"}]},"doc://DotFaceCore/documentation/DotFaceCore/HeadPoseAttribute":{"identifier":"doc:\/\/DotFaceCore\/documentation\/DotFaceCore\/HeadPoseAttribute","kind":"symbol","type":"topic","role":"symbol","navigatorTitle":[{"kind":"identifier","text":"HeadPoseAttribute"}],"title":"HeadPoseAttribute","url":"\/documentation\/dotfacecore\/headposeattribute","abstract":[{"text":"Head pose attribute with angle value instead of score.","type":"text"}],"fragments":[{"kind":"keyword","text":"class"},{"kind":"text","text":" "},{"kind":"identifier","text":"HeadPoseAttribute"}]},"doc://DotFaceCore/documentation/DotFaceCore/BgraRawImage":{"kind":"symbol","fragments":[{"kind":"keyword","text":"class"},{"text":" ","kind":"text"},{"kind":"identifier","text":"BgraRawImage"}],"url":"\/documentation\/dotfacecore\/bgrarawimage","identifier":"doc:\/\/DotFaceCore\/documentation\/DotFaceCore\/BgraRawImage","type":"topic","navigatorTitle":[{"kind":"identifier","text":"BgraRawImage"}],"abstract":[{"type":"text","text":"Raw image with BGRA8888 pixel format."}],"role":"symbol","title":"BgraRawImage"},"doc://DotFaceCore/documentation/DotFaceCore/DOTFFaceAutoCaptureConfigurationPresets":{"type":"topic","kind":"symbol","fragments":[{"text":"DOTFFaceAutoCaptureConfigurationPresets","kind":"identifier"}],"abstract":[{"text":"Pre-defined sets of configurations.","type":"text"}],"url":"\/documentation\/dotfacecore\/dotffaceautocaptureconfigurationpresets","title":"DOTFFaceAutoCaptureConfigurationPresets","role":"symbol","identifier":"doc:\/\/DotFaceCore\/documentation\/DotFaceCore\/DOTFFaceAutoCaptureConfigurationPresets"},"doc://DotFaceCore/documentation/DotFaceCore/DotCoreVersionNumber":{"fragments":[{"text":"DotCoreVersionNumber","kind":"identifier"}],"kind":"symbol","url":"\/documentation\/dotfacecore\/dotcoreversionnumber","abstract":[{"text":"Project version number for DotCore.","type":"text"}],"type":"topic","role":"symbol","identifier":"doc:\/\/DotFaceCore\/documentation\/DotFaceCore\/DotCoreVersionNumber","title":"DotCoreVersionNumber"},"doc://DotFaceCore/documentation/DotFaceCore/DotFaceCoreVersionNumber":{"title":"DotFaceCoreVersionNumber","fragments":[{"text":"DotFaceCoreVersionNumber","kind":"identifier"}],"type":"topic","identifier":"doc:\/\/DotFaceCore\/documentation\/DotFaceCore\/DotFaceCoreVersionNumber","abstract":[{"type":"text","text":"Project version number for DotFaceCore."}],"role":"symbol","kind":"symbol","url":"\/documentation\/dotfacecore\/dotfacecoreversionnumber"},"doc://DotFaceCore/documentation/DotFaceCore/BgraRawImageFactory":{"url":"\/documentation\/dotfacecore\/bgrarawimagefactory","fragments":[{"kind":"keyword","text":"class"},{"text":" ","kind":"text"},{"kind":"identifier","text":"BgraRawImageFactory"}],"title":"BgraRawImageFactory","abstract":[{"text":"Create ","type":"text"},{"type":"codeVoice","code":"BgraRawImage"},{"text":" from iOS native image types.","type":"text"}],"identifier":"doc:\/\/DotFaceCore\/documentation\/DotFaceCore\/BgraRawImageFactory","role":"symbol","type":"topic","navigatorTitle":[{"text":"BgraRawImageFactory","kind":"identifier"}],"kind":"symbol"},"doc://DotFaceCore/documentation/DotFaceCore/MagnifEyeLivenessViewController":{"navigatorTitle":[{"kind":"identifier","text":"MagnifEyeLivenessViewController"}],"fragments":[{"kind":"keyword","text":"class"},{"kind":"text","text":" "},{"kind":"identifier","text":"MagnifEyeLivenessViewController"}],"title":"MagnifEyeLivenessViewController","identifier":"doc:\/\/DotFaceCore\/documentation\/DotFaceCore\/MagnifEyeLivenessViewController","kind":"symbol","url":"\/documentation\/dotfacecore\/magnifeyelivenessviewcontroller","role":"symbol","type":"topic","abstract":[{"type":"text","text":"UI component for capturing images suitable for MagnifEye liveness evaluation."}]},"doc://DotFaceCore/documentation/DotFaceCore/DOTFTemplateMatcherResult":{"url":"\/documentation\/dotfacecore\/dotftemplatematcherresult","type":"topic","title":"DOTFTemplateMatcherResult","kind":"symbol","identifier":"doc:\/\/DotFaceCore\/documentation\/DotFaceCore\/DOTFTemplateMatcherResult","abstract":[{"type":"text","text":"Template matcher result."}],"role":"symbol","fragments":[{"text":"DOTFTemplateMatcherResult","kind":"identifier"}]},"doc://DotFaceCore/documentation/DotFaceCore/EyesExpressionQuery":{"identifier":"doc:\/\/DotFaceCore\/documentation\/DotFaceCore\/EyesExpressionQuery","kind":"symbol","type":"topic","role":"symbol","navigatorTitle":[{"kind":"identifier","text":"EyesExpressionQuery"}],"title":"EyesExpressionQuery","url":"\/documentation\/dotfacecore\/eyesexpressionquery","abstract":[{"text":"Eyes expression query specifies which eye expression face attributes should be evaluated.","type":"text"}],"fragments":[{"kind":"keyword","text":"class"},{"kind":"text","text":" "},{"kind":"identifier","text":"EyesExpressionQuery"}]},"doc://DotFaceCore/documentation/DotFaceCore/DotFaceLibrary":{"type":"topic","role":"symbol","navigatorTitle":[{"kind":"identifier","text":"DotFaceLibrary"}],"fragments":[{"text":"class","kind":"keyword"},{"kind":"text","text":" "},{"text":"DotFaceLibrary","kind":"identifier"}],"abstract":[{"type":"text","text":"Class responsible for the "},{"type":"codeVoice","code":"DotFace"},{"type":"text","text":" library initialization."}],"kind":"symbol","identifier":"doc:\/\/DotFaceCore\/documentation\/DotFaceCore\/DotFaceLibrary","url":"\/documentation\/dotfacecore\/dotfacelibrary","title":"DotFaceLibrary"},"doc://DotFaceCore/documentation/DotFaceCore/DotLibraryId":{"identifier":"doc:\/\/DotFaceCore\/documentation\/DotFaceCore\/DotLibraryId","kind":"symbol","role":"symbol","type":"topic","navigatorTitle":[{"kind":"identifier","text":"DotLibraryId"}],"title":"DotLibraryId","url":"\/documentation\/dotfacecore\/dotlibraryid","abstract":[{"text":"The ","type":"text"},{"code":"DotSdk","type":"codeVoice"},{"type":"text","text":" library identifier."}],"fragments":[{"kind":"keyword","text":"enum"},{"kind":"text","text":" "},{"kind":"identifier","text":"DotLibraryId"}]},"doc://DotFaceCore/documentation/DotFaceCore/DotSdk":{"identifier":"doc:\/\/DotFaceCore\/documentation\/DotFaceCore\/DotSdk","fragments":[{"text":"class","kind":"keyword"},{"kind":"text","text":" "},{"text":"DotSdk","kind":"identifier"}],"abstract":[{"type":"text","text":"Class responsible for the initialization of DOT libraries - "},{"code":"DotFace","type":"codeVoice"},{"type":"text","text":", "},{"type":"codeVoice","code":"DotFaceLite"},{"text":", ","type":"text"},{"code":"DotDocument","type":"codeVoice"},{"type":"text","text":", "},{"code":"DotNfc","type":"codeVoice"},{"text":", ","type":"text"},{"type":"codeVoice","code":"DotPalm"},{"type":"text","text":"."}],"url":"\/documentation\/dotfacecore\/dotsdk","title":"DotSdk","type":"topic","role":"symbol","kind":"symbol","navigatorTitle":[{"text":"DotSdk","kind":"identifier"}]},"doc://DotFaceCore/documentation/DotFaceCore/ExpressionQuery":{"title":"ExpressionQuery","navigatorTitle":[{"kind":"identifier","text":"ExpressionQuery"}],"identifier":"doc:\/\/DotFaceCore\/documentation\/DotFaceCore\/ExpressionQuery","type":"topic","role":"symbol","fragments":[{"text":"class","kind":"keyword"},{"kind":"text","text":" "},{"kind":"identifier","text":"ExpressionQuery"}],"abstract":[{"text":"Expression query specifies which face expression face attributes should be evaluated.","type":"text"}],"kind":"symbol","url":"\/documentation\/dotfacecore\/expressionquery"},"doc://DotFaceCore/documentation/DotFaceCore/EyeGazeLivenessResult":{"kind":"symbol","url":"\/documentation\/dotfacecore\/eyegazelivenessresult","role":"symbol","navigatorTitle":[{"text":"EyeGazeLivenessResult","kind":"identifier"}],"fragments":[{"text":"class","kind":"keyword"},{"text":" ","kind":"text"},{"text":"EyeGazeLivenessResult","kind":"identifier"}],"title":"EyeGazeLivenessResult","type":"topic","identifier":"doc:\/\/DotFaceCore\/documentation\/DotFaceCore\/EyeGazeLivenessResult","abstract":[{"text":"The final result of the eye gaze liveness process.","type":"text"}]},"doc://DotFaceCore/documentation/DotFaceCore/FaceFeature":{"abstract":[{"text":"Available face features.","type":"text"}],"fragments":[{"text":"enum","kind":"keyword"},{"text":" ","kind":"text"},{"text":"FaceFeature","kind":"identifier"}],"type":"topic","kind":"symbol","identifier":"doc:\/\/DotFaceCore\/documentation\/DotFaceCore\/FaceFeature","role":"symbol","url":"\/documentation\/dotfacecore\/facefeature","navigatorTitle":[{"text":"FaceFeature","kind":"identifier"}],"title":"FaceFeature"},"doc://DotFaceCore/documentation/DotFaceCore/EyeGazeLivenessCorner":{"title":"EyeGazeLivenessCorner","identifier":"doc:\/\/DotFaceCore\/documentation\/DotFaceCore\/EyeGazeLivenessCorner","role":"symbol","navigatorTitle":[{"text":"EyeGazeLivenessCorner","kind":"identifier"}],"fragments":[{"text":"enum","kind":"keyword"},{"kind":"text","text":" "},{"kind":"identifier","text":"EyeGazeLivenessCorner"}],"abstract":[{"type":"text","text":"Eye gaze liveness corner."}],"kind":"symbol","type":"topic","url":"\/documentation\/dotfacecore\/eyegazelivenesscorner"},"doc://DotFaceCore/documentation/DotFaceCore/FaceMatcher":{"abstract":[{"text":"Stateless class which can match face images and templates.","type":"text"}],"title":"FaceMatcher","identifier":"doc:\/\/DotFaceCore\/documentation\/DotFaceCore\/FaceMatcher","navigatorTitle":[{"text":"FaceMatcher","kind":"identifier"}],"url":"\/documentation\/dotfacecore\/facematcher","fragments":[{"text":"class","kind":"keyword"},{"kind":"text","text":" "},{"text":"FaceMatcher","kind":"identifier"}],"type":"topic","role":"symbol","kind":"symbol"},"doc://DotFaceCore/documentation/DotFaceCore/DotFaceModule":{"abstract":[{"code":"DotFace","type":"codeVoice"},{"type":"text","text":" feature module."}],"role":"symbol","fragments":[{"text":"protocol","kind":"keyword"},{"kind":"text","text":" "},{"text":"DotFaceModule","kind":"identifier"}],"type":"topic","title":"DotFaceModule","url":"\/documentation\/dotfacecore\/dotfacemodule","kind":"symbol","navigatorTitle":[{"kind":"identifier","text":"DotFaceModule"}],"identifier":"doc:\/\/DotFaceCore\/documentation\/DotFaceCore\/DotFaceModule"},"doc://DotFaceCore/documentation/DotFaceCore/CGImageFactory":{"fragments":[{"text":"class","kind":"keyword"},{"text":" ","kind":"text"},{"text":"CGImageFactory","kind":"identifier"}],"kind":"symbol","role":"symbol","url":"\/documentation\/dotfacecore\/cgimagefactory","identifier":"doc:\/\/DotFaceCore\/documentation\/DotFaceCore\/CGImageFactory","navigatorTitle":[{"kind":"identifier","text":"CGImageFactory"}],"title":"CGImageFactory","abstract":[{"type":"text","text":"Create "},{"code":"CGImage","type":"codeVoice"},{"text":" from ","type":"text"},{"code":"BgraRawImage","type":"codeVoice"},{"type":"text","text":" or "},{"code":"BgrRawImage","type":"codeVoice"},{"text":".","type":"text"}],"type":"topic"},"doc://DotFaceCore/documentation/DotFaceCore/HeadPose":{"identifier":"doc:\/\/DotFaceCore\/documentation\/DotFaceCore\/HeadPose","kind":"symbol","type":"topic","role":"symbol","navigatorTitle":[{"kind":"identifier","text":"HeadPose"}],"title":"HeadPose","url":"\/documentation\/dotfacecore\/headpose","abstract":[{"text":"Head pose evaluation result. Contains evaluated face attributes which represent the head pose of the detected face.","type":"text"}],"fragments":[{"kind":"keyword","text":"class"},{"kind":"text","text":" "},{"kind":"identifier","text":"HeadPose"}]},"doc://DotFaceCore/documentation/DotFaceCore/DOTFEyeGazeLivenessTransitionType":{"type":"topic","kind":"symbol","title":"DOTFEyeGazeLivenessTransitionType","identifier":"doc:\/\/DotFaceCore\/documentation\/DotFaceCore\/DOTFEyeGazeLivenessTransitionType","url":"\/documentation\/dotfacecore\/dotfeyegazelivenesstransitiontype","fragments":[{"text":"DOTFEyeGazeLivenessTransitionType","kind":"identifier"}],"role":"symbol","abstract":[{"type":"text","text":"Eye gaze liveness available corner transition types."}]},"doc://DotFaceCore/documentation/DotFaceCore/PlaceholderStyle":{"abstract":[],"kind":"symbol","identifier":"doc:\/\/DotFaceCore\/documentation\/DotFaceCore\/PlaceholderStyle","fragments":[{"text":"class","kind":"keyword"},{"kind":"text","text":" "},{"text":"PlaceholderStyle","kind":"identifier"}],"type":"topic","navigatorTitle":[{"kind":"identifier","text":"PlaceholderStyle"}],"url":"\/documentation\/dotfacecore\/placeholderstyle","role":"symbol","title":"PlaceholderStyle"},"doc://DotFaceCore/documentation/DotFaceCore/RandomEyeGazeLivenessCornersGenerator":{"kind":"symbol","role":"symbol","url":"\/documentation\/dotfacecore\/randomeyegazelivenesscornersgenerator","fragments":[{"kind":"keyword","text":"class"},{"kind":"text","text":" "},{"kind":"identifier","text":"RandomEyeGazeLivenessCornersGenerator"}],"identifier":"doc:\/\/DotFaceCore\/documentation\/DotFaceCore\/RandomEyeGazeLivenessCornersGenerator","title":"RandomEyeGazeLivenessCornersGenerator","type":"topic","navigatorTitle":[{"text":"RandomEyeGazeLivenessCornersGenerator","kind":"identifier"}],"abstract":[{"text":"Generates random corners for the eye gaze liveness process.","type":"text"}]},"doc://DotFaceCore/documentation/DotFaceCore/DotFaceModuleId":{"kind":"symbol","url":"\/documentation\/dotfacecore\/dotfacemoduleid","role":"symbol","navigatorTitle":[{"kind":"identifier","text":"DotFaceModuleId"}],"fragments":[{"text":"enum","kind":"keyword"},{"text":" ","kind":"text"},{"kind":"identifier","text":"DotFaceModuleId"}],"title":"DotFaceModuleId","type":"topic","identifier":"doc:\/\/DotFaceCore\/documentation\/DotFaceCore\/DotFaceModuleId","abstract":[{"code":"DotFace","type":"codeVoice"},{"type":"text","text":" feature module identifier."}]},"doc://DotFaceCore/documentation/DotFaceCore/WrappedEyeGazeLivenessCorner":{"identifier":"doc:\/\/DotFaceCore\/documentation\/DotFaceCore\/WrappedEyeGazeLivenessCorner","title":"WrappedEyeGazeLivenessCorner","abstract":[{"text":"Objective-C wrapper of ","type":"text"},{"type":"codeVoice","code":"EyeGazeLivenessCorner"},{"type":"text","text":"."}],"fragments":[{"kind":"keyword","text":"class"},{"text":" ","kind":"text"},{"text":"WrappedEyeGazeLivenessCorner","kind":"identifier"}],"kind":"symbol","url":"\/documentation\/dotfacecore\/wrappedeyegazelivenesscorner","type":"topic","navigatorTitle":[{"kind":"identifier","text":"WrappedEyeGazeLivenessCorner"}],"role":"symbol"},"doc://DotFaceCore/documentation/DotFaceCore/InstructionStyle":{"url":"\/documentation\/dotfacecore\/instructionstyle","fragments":[{"kind":"keyword","text":"class"},{"text":" ","kind":"text"},{"text":"InstructionStyle","kind":"identifier"}],"title":"InstructionStyle","kind":"symbol","role":"symbol","abstract":[],"type":"topic","identifier":"doc:\/\/DotFaceCore\/documentation\/DotFaceCore\/InstructionStyle","navigatorTitle":[{"kind":"identifier","text":"InstructionStyle"}]},"doc://DotFaceCore/documentation/DotFaceCore/RectangleDouble":{"type":"topic","url":"\/documentation\/dotfacecore\/rectangledouble","kind":"symbol","navigatorTitle":[{"text":"RectangleDouble","kind":"identifier"}],"title":"RectangleDouble","role":"symbol","identifier":"doc:\/\/DotFaceCore\/documentation\/DotFaceCore\/RectangleDouble","abstract":[{"type":"text","text":"Rectangle area defined by the edges with "},{"code":"Double","type":"codeVoice"},{"type":"text","text":" value type."}],"fragments":[{"kind":"keyword","text":"class"},{"text":" ","kind":"text"},{"text":"RectangleDouble","kind":"identifier"}]},"doc://DotFaceCore/documentation/DotFaceCore/DotLibrary":{"kind":"symbol","title":"DotLibrary","url":"\/documentation\/dotfacecore\/dotlibrary","navigatorTitle":[{"text":"DotLibrary","kind":"identifier"}],"abstract":[],"role":"symbol","identifier":"doc:\/\/DotFaceCore\/documentation\/DotFaceCore\/DotLibrary","type":"topic","fragments":[{"text":"protocol","kind":"keyword"},{"text":" ","kind":"text"},{"text":"DotLibrary","kind":"identifier"}]},"doc://DotFaceCore/documentation/DotFaceCore/FaceAutoCaptureViewController":{"navigatorTitle":[{"text":"FaceAutoCaptureViewController","kind":"identifier"}],"role":"symbol","identifier":"doc:\/\/DotFaceCore\/documentation\/DotFaceCore\/FaceAutoCaptureViewController","kind":"symbol","fragments":[{"text":"class","kind":"keyword"},{"kind":"text","text":" "},{"kind":"identifier","text":"FaceAutoCaptureViewController"}],"abstract":[{"type":"text","text":"UI component for capturing high quality face images using the placeholder."}],"title":"FaceAutoCaptureViewController","type":"topic","url":"\/documentation\/dotfacecore\/faceautocaptureviewcontroller"},"doc://DotFaceCore/documentation/DotFaceCore/DotCaptureVersionString":{"abstract":[{"type":"text","text":"Project version string for DotCapture."}],"role":"symbol","fragments":[{"text":"DotCaptureVersionString","kind":"identifier"}],"type":"topic","title":"DotCaptureVersionString","url":"\/documentation\/dotfacecore\/dotcaptureversionstring","kind":"symbol","identifier":"doc:\/\/DotFaceCore\/documentation\/DotFaceCore\/DotCaptureVersionString"},"doc://DotFaceCore/documentation/DotFaceCore/FaceFeatureWrapper":{"identifier":"doc:\/\/DotFaceCore\/documentation\/DotFaceCore\/FaceFeatureWrapper","type":"topic","role":"symbol","fragments":[{"kind":"keyword","text":"class"},{"text":" ","kind":"text"},{"text":"FaceFeatureWrapper","kind":"identifier"}],"kind":"symbol","url":"\/documentation\/dotfacecore\/facefeaturewrapper","abstract":[{"type":"text","text":"Face feature wrapper."}],"title":"FaceFeatureWrapper","navigatorTitle":[{"kind":"identifier","text":"FaceFeatureWrapper"}]},"doc://DotFaceCore/documentation/DotFaceCore/CaptureMode":{"url":"\/documentation\/dotfacecore\/capturemode","type":"topic","identifier":"doc:\/\/DotFaceCore\/documentation\/DotFaceCore\/CaptureMode","role":"symbol","title":"CaptureMode","navigatorTitle":[{"kind":"identifier","text":"CaptureMode"}],"fragments":[{"text":"enum","kind":"keyword"},{"text":" ","kind":"text"},{"kind":"identifier","text":"CaptureMode"}],"kind":"symbol","abstract":[{"type":"text","text":"Capture mode."}]},"doc://DotFaceCore/documentation/DotFaceCore/CameraPreviewScaleType":{"title":"CameraPreviewScaleType","type":"topic","fragments":[{"text":"enum","kind":"keyword"},{"kind":"text","text":" "},{"kind":"identifier","text":"CameraPreviewScaleType"}],"abstract":[{"type":"text","text":"Indicates how the layer displays video frames."}],"url":"\/documentation\/dotfacecore\/camerapreviewscaletype","role":"symbol","navigatorTitle":[{"kind":"identifier","text":"CameraPreviewScaleType"}],"identifier":"doc:\/\/DotFaceCore\/documentation\/DotFaceCore\/CameraPreviewScaleType","kind":"symbol"},"doc://DotFaceCore/documentation/DotFaceCore/EyesExpression":{"identifier":"doc:\/\/DotFaceCore\/documentation\/DotFaceCore\/EyesExpression","type":"topic","kind":"symbol","role":"symbol","navigatorTitle":[{"kind":"identifier","text":"EyesExpression"}],"title":"EyesExpression","url":"\/documentation\/dotfacecore\/eyesexpression","abstract":[{"type":"text","text":"Eyes expression evaluation result."}],"fragments":[{"kind":"keyword","text":"class"},{"kind":"text","text":" "},{"kind":"identifier","text":"EyesExpression"}]},"doc://DotFaceCore/documentation/DotFaceCore/DOTFSmileLivenessStyle":{"identifier":"doc:\/\/DotFaceCore\/documentation\/DotFaceCore\/DOTFSmileLivenessStyle","kind":"symbol","title":"DOTFSmileLivenessStyle","abstract":[{"type":"text","text":"Customization options for the smile liveness user interface."}],"url":"\/documentation\/dotfacecore\/dotfsmilelivenessstyle","role":"symbol","fragments":[{"text":"DOTFSmileLivenessStyle","kind":"identifier"}],"type":"topic"},"doc://DotFaceCore/documentation/DotFaceCore/DotFaceCommonsVersionNumber":{"kind":"symbol","title":"DotFaceCommonsVersionNumber","type":"topic","identifier":"doc:\/\/DotFaceCore\/documentation\/DotFaceCore\/DotFaceCommonsVersionNumber","url":"\/documentation\/dotfacecore\/dotfacecommonsversionnumber","abstract":[{"type":"text","text":"Project version number for DotFaceCommons."}],"fragments":[{"text":"DotFaceCommonsVersionNumber","kind":"identifier"}],"role":"symbol"},"doc://DotFaceCore/documentation/DotFaceCore/EyeGazeLivenessCornersGenerator":{"type":"topic","url":"\/documentation\/dotfacecore\/eyegazelivenesscornersgenerator","kind":"symbol","navigatorTitle":[{"text":"EyeGazeLivenessCornersGenerator","kind":"identifier"}],"abstract":[{"text":"Generates corners for the eye gaze liveness process.","type":"text"}],"role":"symbol","title":"EyeGazeLivenessCornersGenerator","fragments":[{"text":"protocol","kind":"keyword"},{"kind":"text","text":" "},{"kind":"identifier","text":"EyeGazeLivenessCornersGenerator"}],"identifier":"doc:\/\/DotFaceCore\/documentation\/DotFaceCore\/EyeGazeLivenessCornersGenerator"},"doc://DotFaceCore/documentation/DotFaceCore/Face":{"fragments":[{"kind":"identifier","text":"Face"}],"title":"Face","identifier":"doc:\/\/DotFaceCore\/documentation\/DotFaceCore\/Face","kind":"symbol","url":"\/documentation\/dotfacecore\/face","role":"symbol","type":"topic","abstract":[{"type":"text","text":"Detected face in the image."}]},"doc://DotFaceCore/documentation/DotFaceCore/FaceImageQualityQuery":{"identifier":"doc:\/\/DotFaceCore\/documentation\/DotFaceCore\/FaceImageQualityQuery","type":"topic","kind":"symbol","role":"symbol","navigatorTitle":[{"kind":"identifier","text":"FaceImageQualityQuery"}],"title":"FaceImageQualityQuery","url":"\/documentation\/dotfacecore\/faceimagequalityquery","abstract":[{"type":"text","text":"Face image quality query specifies which face image quality face attributes should be evaluated."}],"fragments":[{"kind":"keyword","text":"class"},{"kind":"text","text":" "},{"kind":"identifier","text":"FaceImageQualityQuery"}]},"doc://DotFaceCore/documentation/DotFaceCore/DOTFTemplateVersion":{"url":"\/documentation\/dotfacecore\/dotftemplateversion","title":"DOTFTemplateVersion","abstract":[{"text":"Template compatibility version.","type":"text"}],"fragments":[{"text":"DOTFTemplateVersion","kind":"identifier"}],"type":"topic","identifier":"doc:\/\/DotFaceCore\/documentation\/DotFaceCore\/DOTFTemplateVersion","kind":"symbol","role":"symbol"},"doc://DotFaceCore/documentation/DotFaceCore/LoggerLogLevel":{"kind":"symbol","fragments":[{"kind":"keyword","text":"enum"},{"text":" ","kind":"text"},{"kind":"identifier","text":"LoggerLogLevel"}],"role":"symbol","title":"LoggerLogLevel","navigatorTitle":[{"kind":"identifier","text":"LoggerLogLevel"}],"abstract":[{"text":"Available log levels.","type":"text"}],"type":"topic","url":"\/documentation\/dotfacecore\/loggerloglevel","identifier":"doc:\/\/DotFaceCore\/documentation\/DotFaceCore\/LoggerLogLevel"},"doc://DotFaceCore/documentation/DotFaceCore/FaceQuality":{"identifier":"doc:\/\/DotFaceCore\/documentation\/DotFaceCore\/FaceQuality","kind":"symbol","type":"topic","role":"symbol","navigatorTitle":[{"kind":"identifier","text":"FaceQuality"}],"title":"FaceQuality","url":"\/documentation\/dotfacecore\/facequality","abstract":[{"text":"Face quality evaluation result. Contains all the evaluated face attributes which together represent the face quality.","type":"text"}],"fragments":[{"kind":"keyword","text":"class"},{"kind":"text","text":" "},{"kind":"identifier","text":"FaceQuality"}]},"doc://DotFaceCore/documentation/DotFaceCore/InstructionCandidateSelectionStyle":{"url":"\/documentation\/dotfacecore\/instructioncandidateselectionstyle","fragments":[{"kind":"keyword","text":"class"},{"text":" ","kind":"text"},{"text":"InstructionCandidateSelectionStyle","kind":"identifier"}],"title":"InstructionCandidateSelectionStyle","kind":"symbol","role":"symbol","type":"topic","abstract":[],"identifier":"doc:\/\/DotFaceCore\/documentation\/DotFaceCore\/InstructionCandidateSelectionStyle","navigatorTitle":[{"kind":"identifier","text":"InstructionCandidateSelectionStyle"}]},"doc://DotFaceCore/documentation/DotFaceCore/WrappedFloat":{"role":"symbol","type":"topic","identifier":"doc:\/\/DotFaceCore\/documentation\/DotFaceCore\/WrappedFloat","url":"\/documentation\/dotfacecore\/wrappedfloat","navigatorTitle":[{"kind":"identifier","text":"WrappedFloat"}],"kind":"symbol","abstract":[{"type":"text","text":"Wrapped "},{"type":"codeVoice","code":"Float"},{"text":" value for Objective-C support.","type":"text"}],"title":"WrappedFloat","fragments":[{"kind":"keyword","text":"class"},{"text":" ","kind":"text"},{"kind":"identifier","text":"WrappedFloat"}]},"doc://DotFaceCore/documentation/DotFaceCore/CIImageFactory":{"role":"symbol","abstract":[{"type":"text","text":"Create "},{"type":"codeVoice","code":"CIImage"},{"type":"text","text":" from "},{"type":"codeVoice","code":"BgraRawImage"},{"type":"text","text":" or "},{"code":"BgrRawImage","type":"codeVoice"},{"text":".","type":"text"}],"identifier":"doc:\/\/DotFaceCore\/documentation\/DotFaceCore\/CIImageFactory","fragments":[{"kind":"keyword","text":"class"},{"text":" ","kind":"text"},{"text":"CIImageFactory","kind":"identifier"}],"title":"CIImageFactory","type":"topic","kind":"symbol","url":"\/documentation\/dotfacecore\/ciimagefactory","navigatorTitle":[{"kind":"identifier","text":"CIImageFactory"}]},"doc://DotFaceCore/documentation/DotFaceCore/DOTFFaceSimpleCaptureStyle":{"abstract":[{"type":"text","text":"Customization options for the face simple capture user interface."}],"type":"topic","identifier":"doc:\/\/DotFaceCore\/documentation\/DotFaceCore\/DOTFFaceSimpleCaptureStyle","kind":"symbol","url":"\/documentation\/dotfacecore\/dotffacesimplecapturestyle","title":"DOTFFaceSimpleCaptureStyle","role":"symbol","fragments":[{"text":"DOTFFaceSimpleCaptureStyle","kind":"identifier"}]},"doc://DotFaceCore/documentation/DotFaceCore/TimedCaptureEvaluator":{"abstract":[],"role":"symbol","fragments":[{"kind":"keyword","text":"protocol"},{"text":" ","kind":"text"},{"kind":"identifier","text":"TimedCaptureEvaluator"}],"type":"topic","title":"TimedCaptureEvaluator","kind":"symbol","url":"\/documentation\/dotfacecore\/timedcaptureevaluator","navigatorTitle":[{"text":"TimedCaptureEvaluator","kind":"identifier"}],"identifier":"doc:\/\/DotFaceCore\/documentation\/DotFaceCore\/TimedCaptureEvaluator"},"doc://DotFaceCore/documentation/DotFaceCore/FaceAspects":{"title":"FaceAspects","navigatorTitle":[{"kind":"identifier","text":"FaceAspects"}],"identifier":"doc:\/\/DotFaceCore\/documentation\/DotFaceCore\/FaceAspects","type":"topic","role":"symbol","fragments":[{"kind":"keyword","text":"class"},{"text":" ","kind":"text"},{"kind":"identifier","text":"FaceAspects"}],"abstract":[{"text":"Face aspects represent various static properties of the face.","type":"text"}],"kind":"symbol","url":"\/documentation\/dotfacecore\/faceaspects"},"doc://DotFaceCore/documentation/DotFaceCore/SmileLivenessViewController":{"navigatorTitle":[{"text":"SmileLivenessViewController","kind":"identifier"}],"fragments":[{"kind":"keyword","text":"class"},{"kind":"text","text":" "},{"kind":"identifier","text":"SmileLivenessViewController"}],"identifier":"doc:\/\/DotFaceCore\/documentation\/DotFaceCore\/SmileLivenessViewController","title":"SmileLivenessViewController","abstract":[{"type":"text","text":"UI component for evaluating liveness by detecting face expression."}],"kind":"symbol","type":"topic","role":"symbol","url":"\/documentation\/dotfacecore\/smilelivenessviewcontroller"},"doc://DotFaceCore/documentation/DotFaceCore/FaceSimpleCaptureViewController":{"navigatorTitle":[{"text":"FaceSimpleCaptureViewController","kind":"identifier"}],"fragments":[{"text":"class","kind":"keyword"},{"text":" ","kind":"text"},{"kind":"identifier","text":"FaceSimpleCaptureViewController"}],"title":"FaceSimpleCaptureViewController","kind":"symbol","abstract":[{"text":"UI component for capturing face images.","type":"text"}],"role":"symbol","url":"\/documentation\/dotfacecore\/facesimplecaptureviewcontroller","identifier":"doc:\/\/DotFaceCore\/documentation\/DotFaceCore\/FaceSimpleCaptureViewController","type":"topic","deprecated":true},"doc://DotFaceCore/documentation/DotFaceCore/DOTFValueRangeStatus":{"title":"DOTFValueRangeStatus","type":"topic","abstract":[{"text":"Status of a value with respect to a range.","type":"text"}],"identifier":"doc:\/\/DotFaceCore\/documentation\/DotFaceCore\/DOTFValueRangeStatus","fragments":[{"text":"DOTFValueRangeStatus","kind":"identifier"}],"url":"\/documentation\/dotfacecore\/dotfvaluerangestatus","kind":"symbol","role":"symbol"},"doc://DotFaceCore/documentation/DotFaceCore/IntervalFloat":{"kind":"symbol","navigatorTitle":[{"text":"IntervalFloat","kind":"identifier"}],"type":"topic","identifier":"doc:\/\/DotFaceCore\/documentation\/DotFaceCore\/IntervalFloat","abstract":[{"text":"Representation of closed interval with value type ","type":"text"},{"type":"codeVoice","code":"Float"},{"type":"text","text":"."},{"type":"text","text":" "},{"type":"text","text":"The "},{"type":"codeVoice","code":"max"},{"type":"text","text":" must be greater than the "},{"type":"codeVoice","code":"min"},{"type":"text","text":"."}],"url":"\/documentation\/dotfacecore\/intervalfloat","title":"IntervalFloat","role":"symbol","fragments":[{"text":"class","kind":"keyword"},{"kind":"text","text":" "},{"text":"IntervalFloat","kind":"identifier"}]},"doc://DotFaceCore/documentation/DotFaceCore/DotCoreVersionString":{"type":"topic","title":"DotCoreVersionString","identifier":"doc:\/\/DotFaceCore\/documentation\/DotFaceCore\/DotCoreVersionString","role":"symbol","fragments":[{"kind":"identifier","text":"DotCoreVersionString"}],"kind":"symbol","abstract":[{"type":"text","text":"Project version string for DotCore."}],"url":"\/documentation\/dotfacecore\/dotcoreversionstring"},"doc://DotFaceCore/documentation/DotFaceCore/DOTFSmileLivenessConfiguration":{"kind":"symbol","type":"topic","url":"\/documentation\/dotfacecore\/dotfsmilelivenessconfiguration","role":"symbol","abstract":[{"type":"text","text":"Configuration options for the smile liveness process."}],"title":"DOTFSmileLivenessConfiguration","identifier":"doc:\/\/DotFaceCore\/documentation\/DotFaceCore\/DOTFSmileLivenessConfiguration","fragments":[{"text":"DOTFSmileLivenessConfiguration","kind":"identifier"}]},"doc://DotFaceCore/documentation/DotFaceCore/WearablesQuery":{"abstract":[{"text":"Wearables query specifies which wearables face attributes should be evaluated.","type":"text"}],"title":"WearablesQuery","type":"topic","role":"symbol","fragments":[{"kind":"keyword","text":"class"},{"text":" ","kind":"text"},{"text":"WearablesQuery","kind":"identifier"}],"url":"\/documentation\/dotfacecore\/wearablesquery","kind":"symbol","navigatorTitle":[{"text":"WearablesQuery","kind":"identifier"}],"identifier":"doc:\/\/DotFaceCore\/documentation\/DotFaceCore\/WearablesQuery"},"doc://DotFaceCore/documentation/DotFaceCore/DotFaceCoreVersionString":{"role":"symbol","type":"topic","fragments":[{"kind":"identifier","text":"DotFaceCoreVersionString"}],"title":"DotFaceCoreVersionString","abstract":[{"text":"Project version string for DotFaceCore.","type":"text"}],"kind":"symbol","identifier":"doc:\/\/DotFaceCore\/documentation\/DotFaceCore\/DotFaceCoreVersionString","url":"\/documentation\/dotfacecore\/dotfacecoreversionstring"},"doc://DotFaceCore/documentation/DotFaceCore/FaceDetector":{"navigatorTitle":[{"kind":"identifier","text":"FaceDetector"}],"fragments":[{"kind":"keyword","text":"class"},{"kind":"text","text":" "},{"kind":"identifier","text":"FaceDetector"}],"title":"FaceDetector","identifier":"doc:\/\/DotFaceCore\/documentation\/DotFaceCore\/FaceDetector","kind":"symbol","url":"\/documentation\/dotfacecore\/facedetector","role":"symbol","type":"topic","abstract":[{"type":"text","text":"Stateless class which can detect faces in an image."}]},"doc://DotFaceCore/documentation/DotFaceCore/HeadPoseQuery":{"identifier":"doc:\/\/DotFaceCore\/documentation\/DotFaceCore\/HeadPoseQuery","type":"topic","kind":"symbol","role":"symbol","navigatorTitle":[{"kind":"identifier","text":"HeadPoseQuery"}],"title":"HeadPoseQuery","url":"\/documentation\/dotfacecore\/headposequery","abstract":[{"type":"text","text":"Head pose query specifies which head pose attributes should be evaluated."}],"fragments":[{"kind":"keyword","text":"class"},{"kind":"text","text":" "},{"kind":"identifier","text":"HeadPoseQuery"}]},"doc://DotFaceCore/documentation/DotFaceCore/FaceDetectionQuery":{"abstract":[{"type":"text","text":"Face detection query. It allows additional processing beyond basic face detection."}],"kind":"symbol","navigatorTitle":[{"text":"FaceDetectionQuery","kind":"identifier"}],"fragments":[{"text":"class","kind":"keyword"},{"kind":"text","text":" "},{"kind":"identifier","text":"FaceDetectionQuery"}],"type":"topic","title":"FaceDetectionQuery","url":"\/documentation\/dotfacecore\/facedetectionquery","identifier":"doc:\/\/DotFaceCore\/documentation\/DotFaceCore\/FaceDetectionQuery","role":"symbol"},"doc://DotFaceCore/documentation/DotFaceCore/BgrRawImage":{"identifier":"doc:\/\/DotFaceCore\/documentation\/DotFaceCore\/BgrRawImage","url":"\/documentation\/dotfacecore\/bgrrawimage","navigatorTitle":[{"kind":"identifier","text":"BgrRawImage"}],"type":"topic","kind":"symbol","abstract":[{"type":"text","text":"Raw image with BGR888 pixel format."}],"fragments":[{"text":"class","kind":"keyword"},{"text":" ","kind":"text"},{"kind":"identifier","text":"BgrRawImage"}],"role":"symbol","title":"BgrRawImage"},"doc://DotFaceCore/documentation/DotFaceCore/Localization":{"type":"topic","title":"Localization","identifier":"doc:\/\/DotFaceCore\/documentation\/DotFaceCore\/Localization","role":"symbol","fragments":[{"kind":"keyword","text":"class"},{"kind":"text","text":" "},{"text":"Localization","kind":"identifier"}],"kind":"symbol","navigatorTitle":[{"kind":"identifier","text":"Localization"}],"abstract":[{"type":"text","text":"Class responsible for the localization of user interface strings."}],"url":"\/documentation\/dotfacecore\/localization"},"doc://DotFaceCore/documentation/DotFaceCore/TiltAngles":{"title":"TiltAngles","type":"topic","abstract":[{"type":"text","text":"Tilt angles."},{"type":"text","text":" "},{"text":"Also see ","type":"text"},{"identifier":"https:\/\/developer.apple.com\/documentation\/coremotion\/getting_raw_accelerometer_events","isActive":true,"type":"reference"},{"type":"text","text":"."}],"identifier":"doc:\/\/DotFaceCore\/documentation\/DotFaceCore\/TiltAngles","fragments":[{"text":"class","kind":"keyword"},{"text":" ","kind":"text"},{"text":"TiltAngles","kind":"identifier"}],"url":"\/documentation\/dotfacecore\/tiltangles","kind":"symbol","navigatorTitle":[{"text":"TiltAngles","kind":"identifier"}],"role":"symbol"},"doc://DotFaceCore/documentation/DotFaceCore/DotSdkLicenseProxyProtocol":{"url":"\/documentation\/dotfacecore\/dotsdklicenseproxyprotocol","fragments":[{"text":"protocol","kind":"keyword"},{"text":" ","kind":"text"},{"kind":"identifier","text":"DotSdkLicenseProxyProtocol"}],"title":"DotSdkLicenseProxyProtocol","kind":"symbol","role":"symbol","type":"topic","abstract":[],"identifier":"doc:\/\/DotFaceCore\/documentation\/DotFaceCore\/DotSdkLicenseProxyProtocol","navigatorTitle":[{"kind":"identifier","text":"DotSdkLicenseProxyProtocol"}]},"doc://DotFaceCore/documentation/DotFaceCore/DotCaptureVersionNumber":{"abstract":[{"text":"Project version number for DotCapture.","type":"text"}],"identifier":"doc:\/\/DotFaceCore\/documentation\/DotFaceCore\/DotCaptureVersionNumber","url":"\/documentation\/dotfacecore\/dotcaptureversionnumber","role":"symbol","fragments":[{"kind":"identifier","text":"DotCaptureVersionNumber"}],"kind":"symbol","title":"DotCaptureVersionNumber","type":"topic"},"doc://DotFaceCore/documentation/DotFaceCore/BgrRawImageFactory":{"fragments":[{"kind":"keyword","text":"class"},{"kind":"text","text":" "},{"text":"BgrRawImageFactory","kind":"identifier"}],"kind":"symbol","role":"symbol","url":"\/documentation\/dotfacecore\/bgrrawimagefactory","identifier":"doc:\/\/DotFaceCore\/documentation\/DotFaceCore\/BgrRawImageFactory","navigatorTitle":[{"text":"BgrRawImageFactory","kind":"identifier"}],"title":"BgrRawImageFactory","abstract":[{"type":"text","text":"Create "},{"code":"BgrRawImage","type":"codeVoice"},{"type":"text","text":" from iOS native image types."}],"type":"topic"},"doc://DotFaceCore/documentation/DotFaceCore/DotFaceCommonsVersionString":{"title":"DotFaceCommonsVersionString","type":"topic","url":"\/documentation\/dotfacecore\/dotfacecommonsversionstring","identifier":"doc:\/\/DotFaceCore\/documentation\/DotFaceCore\/DotFaceCommonsVersionString","abstract":[{"text":"Project version string for DotFaceCommons.","type":"text"}],"kind":"symbol","role":"symbol","fragments":[{"text":"DotFaceCommonsVersionString","kind":"identifier"}]},"doc://DotFaceCore/documentation/DotFaceCore/TemplateMatcher":{"role":"symbol","abstract":[{"type":"text","text":"Stateless class which can match templates."}],"navigatorTitle":[{"text":"TemplateMatcher","kind":"identifier"}],"fragments":[{"kind":"keyword","text":"class"},{"text":" ","kind":"text"},{"kind":"identifier","text":"TemplateMatcher"}],"url":"\/documentation\/dotfacecore\/templatematcher","type":"topic","title":"TemplateMatcher","kind":"symbol","identifier":"doc:\/\/DotFaceCore\/documentation\/DotFaceCore\/TemplateMatcher"},"doc://DotFaceCore/documentation/DotFaceCore/DOTFQualityAttributeThresholdsBuilder":{"title":"DOTFQualityAttributeThresholdsBuilder","abstract":[],"url":"\/documentation\/dotfacecore\/dotfqualityattributethresholdsbuilder","kind":"symbol","fragments":[{"text":"DOTFQualityAttributeThresholdsBuilder","kind":"identifier"}],"type":"topic","identifier":"doc:\/\/DotFaceCore\/documentation\/DotFaceCore\/DOTFQualityAttributeThresholdsBuilder","role":"symbol"},"doc://DotFaceCore/documentation/DotFaceCore/FaceFeaturePoint":{"navigatorTitle":[{"text":"FaceFeaturePoint","kind":"identifier"}],"abstract":[{"text":"Face feature point contains face feature, point and score.","type":"text"}],"title":"FaceFeaturePoint","identifier":"doc:\/\/DotFaceCore\/documentation\/DotFaceCore\/FaceFeaturePoint","type":"topic","url":"\/documentation\/dotfacecore\/facefeaturepoint","fragments":[{"text":"class","kind":"keyword"},{"text":" ","kind":"text"},{"text":"FaceFeaturePoint","kind":"identifier"}],"role":"symbol","kind":"symbol"},"doc://DotFaceCore/documentation/DotFaceCore/PlaceholderCandidateSelectionStyle":{"identifier":"doc:\/\/DotFaceCore\/documentation\/DotFaceCore\/PlaceholderCandidateSelectionStyle","type":"topic","title":"PlaceholderCandidateSelectionStyle","navigatorTitle":[{"text":"PlaceholderCandidateSelectionStyle","kind":"identifier"}],"fragments":[{"text":"class","kind":"keyword"},{"kind":"text","text":" "},{"text":"PlaceholderCandidateSelectionStyle","kind":"identifier"}],"abstract":[],"role":"symbol","url":"\/documentation\/dotfacecore\/placeholdercandidateselectionstyle","kind":"symbol"},"doc://DotFaceCore/documentation/DotFaceCore/DOTFQualityAttributeThresholdPresets":{"url":"\/documentation\/dotfacecore\/dotfqualityattributethresholdpresets","fragments":[{"text":"DOTFQualityAttributeThresholdPresets","kind":"identifier"}],"type":"topic","kind":"symbol","identifier":"doc:\/\/DotFaceCore\/documentation\/DotFaceCore\/DOTFQualityAttributeThresholdPresets","role":"symbol","abstract":[{"text":"Presets for the quality attributes thresholds of the face auto capture result.","type":"text"}],"title":"DOTFQualityAttributeThresholdPresets"},"doc://DotFaceCore/documentation/DotFaceCore/PreviewViewStyle":{"identifier":"doc:\/\/DotFaceCore\/documentation\/DotFaceCore\/PreviewViewStyle","navigatorTitle":[{"text":"PreviewViewStyle","kind":"identifier"}],"kind":"symbol","abstract":[],"title":"PreviewViewStyle","type":"topic","role":"symbol","fragments":[{"text":"class","kind":"keyword"},{"text":" ","kind":"text"},{"text":"PreviewViewStyle","kind":"identifier"}],"url":"\/documentation\/dotfacecore\/previewviewstyle"},"doc://DotFaceCore/documentation/DotFaceCore/EyeGazeLivenessViewController":{"fragments":[{"kind":"keyword","text":"class"},{"text":" ","kind":"text"},{"text":"EyeGazeLivenessViewController","kind":"identifier"}],"title":"EyeGazeLivenessViewController","url":"\/documentation\/dotfacecore\/eyegazelivenessviewcontroller","abstract":[{"type":"text","text":"UI component for evaluating liveness by tracking eye gaze."}],"type":"topic","navigatorTitle":[{"text":"EyeGazeLivenessViewController","kind":"identifier"}],"role":"symbol","identifier":"doc:\/\/DotFaceCore\/documentation\/DotFaceCore\/EyeGazeLivenessViewController","kind":"symbol"},"doc://DotFaceCore/documentation/DotFaceCore/DOTFMagnifEyeLivenessStyle":{"identifier":"doc:\/\/DotFaceCore\/documentation\/DotFaceCore\/DOTFMagnifEyeLivenessStyle","url":"\/documentation\/dotfacecore\/dotfmagnifeyelivenessstyle","type":"topic","role":"symbol","title":"DOTFMagnifEyeLivenessStyle","abstract":[{"type":"text","text":"Customization options for the MagnifEye liveness user interface."}],"kind":"symbol","fragments":[{"kind":"identifier","text":"DOTFMagnifEyeLivenessStyle"}]},"doc://DotFaceCore/documentation/DotFaceCore/WrappedDouble":{"role":"symbol","title":"WrappedDouble","type":"topic","identifier":"doc:\/\/DotFaceCore\/documentation\/DotFaceCore\/WrappedDouble","url":"\/documentation\/dotfacecore\/wrappeddouble","kind":"symbol","navigatorTitle":[{"text":"WrappedDouble","kind":"identifier"}],"fragments":[{"text":"class","kind":"keyword"},{"text":" ","kind":"text"},{"kind":"identifier","text":"WrappedDouble"}],"abstract":[{"type":"text","text":"Wrapped "},{"type":"codeVoice","code":"Double"},{"text":" value for Objective-C support.","type":"text"}]},"doc://DotFaceCore/documentation/DotFaceCore/DOTFQualityAttributeThresholds":{"title":"DOTFQualityAttributeThresholds","abstract":[{"text":"Configure thresholds for the quality attributes of the face auto capture result.","type":"text"},{"text":" ","type":"text"},{"text":"If the threshold property is set to nil, the corresponding quality attribute will not be validated.","type":"text"}],"role":"symbol","type":"topic","identifier":"doc:\/\/DotFaceCore\/documentation\/DotFaceCore\/DOTFQualityAttributeThresholds","fragments":[{"text":"DOTFQualityAttributeThresholds","kind":"identifier"}],"url":"\/documentation\/dotfacecore\/dotfqualityattributethresholds","kind":"symbol"},"doc://DotFaceCore/documentation/DotFaceCore/DotSdkConfiguration":{"title":"DotSdkConfiguration","kind":"symbol","url":"\/documentation\/dotfacecore\/dotsdkconfiguration","navigatorTitle":[{"kind":"identifier","text":"DotSdkConfiguration"}],"abstract":[{"type":"text","text":"The "},{"code":"DotSdk","type":"codeVoice"},{"text":" configuration.","type":"text"}],"role":"symbol","identifier":"doc:\/\/DotFaceCore\/documentation\/DotFaceCore\/DotSdkConfiguration","type":"topic","fragments":[{"text":"class","kind":"keyword"},{"text":" ","kind":"text"},{"kind":"identifier","text":"DotSdkConfiguration"}]},"doc://DotFaceCore/documentation/DotFaceCore/DOTFEyeGazeLivenessStyle":{"abstract":[{"type":"text","text":"Customization options for the eye gaze liveness user interface."}],"type":"topic","identifier":"doc:\/\/DotFaceCore\/documentation\/DotFaceCore\/DOTFEyeGazeLivenessStyle","kind":"symbol","title":"DOTFEyeGazeLivenessStyle","url":"\/documentation\/dotfacecore\/dotfeyegazelivenessstyle","role":"symbol","fragments":[{"kind":"identifier","text":"DOTFEyeGazeLivenessStyle"}]}},"variantOverrides":[{"traits":[{"interfaceLanguage":"occ"}],"patch":[{"op":"replace","path":"\/identifier\/interfaceLanguage","value":"occ"},{"op":"replace","value":[{"title":"DotFace modularization","identifiers":["doc:\/\/DotFaceCore\/documentation\/DotFaceCore\/DotFaceModule","doc:\/\/DotFaceCore\/documentation\/DotFaceCore\/DotFaceModuleId","doc:\/\/DotFaceCore\/documentation\/DotFaceCore\/DotFaceModuleCategory"]},{"identifiers":["doc:\/\/DotFaceCore\/documentation\/DotFaceCore\/DotFaceLibrary","doc:\/\/DotFaceCore\/documentation\/DotFaceCore\/Logger","doc:\/\/DotFaceCore\/documentation\/DotFaceCore\/Localization"],"title":"Global components"},{"title":"UI components","identifiers":["doc:\/\/DotFaceCore\/documentation\/DotFaceCore\/FaceAutoCaptureViewController","doc:\/\/DotFaceCore\/documentation\/DotFaceCore\/FaceSimpleCaptureViewController","doc:\/\/DotFaceCore\/documentation\/DotFaceCore\/EyeGazeLivenessViewController","doc:\/\/DotFaceCore\/documentation\/DotFaceCore\/SmileLivenessViewController","doc:\/\/DotFaceCore\/documentation\/DotFaceCore\/MagnifEyeLivenessViewController"]},{"identifiers":["doc:\/\/DotFaceCore\/documentation\/DotFaceCore\/FaceDetector","doc:\/\/DotFaceCore\/documentation\/DotFaceCore\/FaceMatcher","doc:\/\/DotFaceCore\/documentation\/DotFaceCore\/TemplateMatcher"],"title":"Non-UI components"},{"identifiers":["doc:\/\/DotFaceCore\/documentation\/DotFaceCore\/FaceAttribute","doc:\/\/DotFaceCore\/documentation\/DotFaceCore\/FaceAspects","doc:\/\/DotFaceCore\/documentation\/DotFaceCore\/FaceQuality","doc:\/\/DotFaceCore\/documentation\/DotFaceCore\/FaceQualityQuery","doc:\/\/DotFaceCore\/documentation\/DotFaceCore\/FaceImageQuality","doc:\/\/DotFaceCore\/documentation\/DotFaceCore\/FaceImageQualityQuery","doc:\/\/DotFaceCore\/documentation\/DotFaceCore\/HeadPose","doc:\/\/DotFaceCore\/documentation\/DotFaceCore\/HeadPoseAttribute","doc:\/\/DotFaceCore\/documentation\/DotFaceCore\/HeadPoseQuery","doc:\/\/DotFaceCore\/documentation\/DotFaceCore\/Expression","doc:\/\/DotFaceCore\/documentation\/DotFaceCore\/EyesExpression","doc:\/\/DotFaceCore\/documentation\/DotFaceCore\/EyesExpressionQuery","doc:\/\/DotFaceCore\/documentation\/DotFaceCore\/ExpressionQuery","doc:\/\/DotFaceCore\/documentation\/DotFaceCore\/Wearables","doc:\/\/DotFaceCore\/documentation\/DotFaceCore\/WearablesQuery","doc:\/\/DotFaceCore\/documentation\/DotFaceCore\/Glasses"],"title":"Face evaluation"},{"title":"Converting images","identifiers":["doc:\/\/DotFaceCore\/documentation\/DotFaceCore\/BgrRawImage","doc:\/\/DotFaceCore\/documentation\/DotFaceCore\/BgrRawImageFactory","doc:\/\/DotFaceCore\/documentation\/DotFaceCore\/CGImageFactory","doc:\/\/DotFaceCore\/documentation\/DotFaceCore\/CIImageFactory"]},{"title":"Classes","identifiers":["doc:\/\/DotFaceCore\/documentation\/DotFaceCore\/BgraRawImage","doc:\/\/DotFaceCore\/documentation\/DotFaceCore\/BgraRawImageFactory","doc:\/\/DotFaceCore\/documentation\/DotFaceCore\/Corners","doc:\/\/DotFaceCore\/documentation\/DotFaceCore\/DOTFEyeGazeLivenessConfiguration","doc:\/\/DotFaceCore\/documentation\/DotFaceCore\/DOTFEyeGazeLivenessStyle","doc:\/\/DotFaceCore\/documentation\/DotFaceCore\/DOTFFaceAutoCaptureConfiguration","doc:\/\/DotFaceCore\/documentation\/DotFaceCore\/DOTFFaceAutoCaptureConfigurationPresets","doc:\/\/DotFaceCore\/documentation\/DotFaceCore\/DOTFFaceAutoCaptureStyle","doc:\/\/DotFaceCore\/documentation\/DotFaceCore\/DOTFFaceMatcherResult","doc:\/\/DotFaceCore\/documentation\/DotFaceCore\/DOTFFaceSimpleCaptureConfiguration","doc:\/\/DotFaceCore\/documentation\/DotFaceCore\/DOTFFaceSimpleCaptureStyle","doc:\/\/DotFaceCore\/documentation\/DotFaceCore\/DOTFMagnifEyeLivenessConfiguration","doc:\/\/DotFaceCore\/documentation\/DotFaceCore\/DOTFMagnifEyeLivenessStyle","doc:\/\/DotFaceCore\/documentation\/DotFaceCore\/DOTFQualityAttributeThresholdPresets","doc:\/\/DotFaceCore\/documentation\/DotFaceCore\/DOTFQualityAttributeThresholds","doc:\/\/DotFaceCore\/documentation\/DotFaceCore\/DOTFQualityAttributeThresholdsBuilder","doc:\/\/DotFaceCore\/documentation\/DotFaceCore\/DOTFSmileLivenessConfiguration","doc:\/\/DotFaceCore\/documentation\/DotFaceCore\/DOTFSmileLivenessStyle","doc:\/\/DotFaceCore\/documentation\/DotFaceCore\/DOTFTemplateMatcherResult","doc:\/\/DotFaceCore\/documentation\/DotFaceCore\/DOTFTemplateVersion","doc:\/\/DotFaceCore\/documentation\/DotFaceCore\/DotFaceModuleCategoryWrapper","doc:\/\/DotFaceCore\/documentation\/DotFaceCore\/DotSdk","doc:\/\/DotFaceCore\/documentation\/DotFaceCore\/DotSdkConfiguration","doc:\/\/DotFaceCore\/documentation\/DotFaceCore\/EyeGazeLivenessResult","doc:\/\/DotFaceCore\/documentation\/DotFaceCore\/Face","doc:\/\/DotFaceCore\/documentation\/DotFaceCore\/FaceDetectionQuery","doc:\/\/DotFaceCore\/documentation\/DotFaceCore\/FaceFeaturePoint","doc:\/\/DotFaceCore\/documentation\/DotFaceCore\/FaceFeatureWrapper","doc:\/\/DotFaceCore\/documentation\/DotFaceCore\/ImageSize","doc:\/\/DotFaceCore\/documentation\/DotFaceCore\/IntervalDouble","doc:\/\/DotFaceCore\/documentation\/DotFaceCore\/IntervalFloat","doc:\/\/DotFaceCore\/documentation\/DotFaceCore\/PointDouble","doc:\/\/DotFaceCore\/documentation\/DotFaceCore\/RandomEyeGazeLivenessCornersGenerator","doc:\/\/DotFaceCore\/documentation\/DotFaceCore\/RectangleDouble","doc:\/\/DotFaceCore\/documentation\/DotFaceCore\/TiltAngles","doc:\/\/DotFaceCore\/documentation\/DotFaceCore\/ValueRange","doc:\/\/DotFaceCore\/documentation\/DotFaceCore\/WrappedDouble","doc:\/\/DotFaceCore\/documentation\/DotFaceCore\/WrappedEyeGazeLivenessCorner","doc:\/\/DotFaceCore\/documentation\/DotFaceCore\/WrappedFloat"]},{"title":"Protocols","identifiers":["doc:\/\/DotFaceCore\/documentation\/DotFaceCore\/DotLibrary","doc:\/\/DotFaceCore\/documentation\/DotFaceCore\/DotSdkLicenseProxyProtocol","doc:\/\/DotFaceCore\/documentation\/DotFaceCore\/EyeGazeLivenessCornersGenerator"]},{"title":"Variables","identifiers":["doc:\/\/DotFaceCore\/documentation\/DotFaceCore\/DotCameraVersionNumber","doc:\/\/DotFaceCore\/documentation\/DotFaceCore\/DotCameraVersionString","doc:\/\/DotFaceCore\/documentation\/DotFaceCore\/DotCaptureVersionNumber","doc:\/\/DotFaceCore\/documentation\/DotFaceCore\/DotCaptureVersionString","doc:\/\/DotFaceCore\/documentation\/DotFaceCore\/DotCoreVersionNumber","doc:\/\/DotFaceCore\/documentation\/DotFaceCore\/DotCoreVersionString","doc:\/\/DotFaceCore\/documentation\/DotFaceCore\/DotFaceCommonsVersionNumber","doc:\/\/DotFaceCore\/documentation\/DotFaceCore\/DotFaceCommonsVersionString","doc:\/\/DotFaceCore\/documentation\/DotFaceCore\/DotFaceCoreVersionNumber","doc:\/\/DotFaceCore\/documentation\/DotFaceCore\/DotFaceCoreVersionString"]},{"identifiers":["doc:\/\/DotFaceCore\/documentation\/DotFaceCore\/CameraFacing","doc:\/\/DotFaceCore\/documentation\/DotFaceCore\/CameraPreviewScaleType","doc:\/\/DotFaceCore\/documentation\/DotFaceCore\/CaptureMode","doc:\/\/DotFaceCore\/documentation\/DotFaceCore\/DOTFEyeGazeLivenessTransitionType","doc:\/\/DotFaceCore\/documentation\/DotFaceCore\/DOTFValueRangeStatus","doc:\/\/DotFaceCore\/documentation\/DotFaceCore\/DotLibraryId","doc:\/\/DotFaceCore\/documentation\/DotFaceCore\/EyeGazeLivenessCorner","doc:\/\/DotFaceCore\/documentation\/DotFaceCore\/FaceFeature","doc:\/\/DotFaceCore\/documentation\/DotFaceCore\/LoggerLogLevel"],"title":"Enumerations"}],"path":"\/topicSections"},{"path":"\/relationshipsSections","op":"add","value":null},{"value":null,"op":"add","path":"\/seeAlsoSections"},{"op":"replace","value":"DotFaceModuleCategory","path":"\/references\/doc:~1~1DotFaceCore~1documentation~1DotFaceCore~1DotFaceModuleCategory\/title"},{"op":"replace","value":[{"text":"DotFaceModuleCategory","kind":"identifier"}],"path":"\/references\/doc:~1~1DotFaceCore~1documentation~1DotFaceCore~1DotFaceModuleCategory\/fragments"},{"op":"replace","path":"\/references\/doc:~1~1DotFaceCore~1documentation~1DotFaceCore~1PointDouble\/title","value":"DOTPointDouble"},{"op":"replace","path":"\/references\/doc:~1~1DotFaceCore~1documentation~1DotFaceCore~1PointDouble\/fragments","value":[{"kind":"identifier","text":"DOTPointDouble"}]},{"value":"DOTFFaceAttribute","op":"replace","path":"\/references\/doc:~1~1DotFaceCore~1documentation~1DotFaceCore~1FaceAttribute\/title"},{"op":"replace","path":"\/references\/doc:~1~1DotFaceCore~1documentation~1DotFaceCore~1FaceAttribute\/fragments","value":[{"kind":"identifier","text":"DOTFFaceAttribute"}]},{"path":"\/references\/doc:~1~1DotFaceCore~1documentation~1DotFaceCore~1FaceImageQuality\/title","op":"replace","value":"DOTFFaceImageQuality"},{"path":"\/references\/doc:~1~1DotFaceCore~1documentation~1DotFaceCore~1FaceImageQuality\/fragments","op":"replace","value":[{"text":"DOTFFaceImageQuality","kind":"identifier"}]},{"op":"replace","path":"\/references\/doc:~1~1DotFaceCore~1documentation~1DotFaceCore~1ImageSize\/title","value":"DOTImageSize"},{"op":"replace","path":"\/references\/doc:~1~1DotFaceCore~1documentation~1DotFaceCore~1ImageSize\/fragments","value":[{"text":"DOTImageSize","kind":"identifier"}]},{"value":"DOTFExpression","op":"replace","path":"\/references\/doc:~1~1DotFaceCore~1documentation~1DotFaceCore~1Expression\/title"},{"value":[{"text":"DOTFExpression","kind":"identifier"}],"path":"\/references\/doc:~1~1DotFaceCore~1documentation~1DotFaceCore~1Expression\/fragments","op":"replace"},{"value":"DOTFGlasses","op":"replace","path":"\/references\/doc:~1~1DotFaceCore~1documentation~1DotFaceCore~1Glasses\/title"},{"op":"replace","path":"\/references\/doc:~1~1DotFaceCore~1documentation~1DotFaceCore~1Glasses\/fragments","value":[{"kind":"identifier","text":"DOTFGlasses"}]},{"op":"replace","path":"\/references\/doc:~1~1DotFaceCore~1documentation~1DotFaceCore~1DotFaceModuleCategoryWrapper\/title","value":"DotFaceModuleCategoryWrapper"},{"op":"replace","value":[{"kind":"identifier","text":"DotFaceModuleCategoryWrapper"}],"path":"\/references\/doc:~1~1DotFaceCore~1documentation~1DotFaceCore~1DotFaceModuleCategoryWrapper\/fragments"},{"value":"DOTIntervalDouble","op":"replace","path":"\/references\/doc:~1~1DotFaceCore~1documentation~1DotFaceCore~1IntervalDouble\/title"},{"op":"replace","value":[{"kind":"identifier","text":"DOTIntervalDouble"}],"path":"\/references\/doc:~1~1DotFaceCore~1documentation~1DotFaceCore~1IntervalDouble\/fragments"},{"path":"\/references\/doc:~1~1DotFaceCore~1documentation~1DotFaceCore~1Wearables\/title","op":"replace","value":"DOTFWearables"},{"value":[{"kind":"identifier","text":"DOTFWearables"}],"op":"replace","path":"\/references\/doc:~1~1DotFaceCore~1documentation~1DotFaceCore~1Wearables\/fragments"},{"op":"replace","value":"DOTFLogger","path":"\/references\/doc:~1~1DotFaceCore~1documentation~1DotFaceCore~1Logger\/title"},{"value":[{"kind":"identifier","text":"DOTFLogger"}],"path":"\/references\/doc:~1~1DotFaceCore~1documentation~1DotFaceCore~1Logger\/fragments","op":"replace"},{"op":"replace","value":"DOTFFaceQualityQuery","path":"\/references\/doc:~1~1DotFaceCore~1documentation~1DotFaceCore~1FaceQualityQuery\/title"},{"path":"\/references\/doc:~1~1DotFaceCore~1documentation~1DotFaceCore~1FaceQualityQuery\/fragments","value":[{"kind":"identifier","text":"DOTFFaceQualityQuery"}],"op":"replace"},{"op":"replace","value":"DOTCameraFacing","path":"\/references\/doc:~1~1DotFaceCore~1documentation~1DotFaceCore~1CameraFacing\/title"},{"value":[{"text":"DOTCameraFacing","kind":"identifier"}],"path":"\/references\/doc:~1~1DotFaceCore~1documentation~1DotFaceCore~1CameraFacing\/fragments","op":"replace"},{"op":"replace","path":"\/references\/doc:~1~1DotFaceCore~1documentation~1DotFaceCore~1Corners\/title","value":"DOTCorners"},{"op":"replace","path":"\/references\/doc:~1~1DotFaceCore~1documentation~1DotFaceCore~1Corners\/fragments","value":[{"text":"DOTCorners","kind":"identifier"}]},{"path":"\/references\/doc:~1~1DotFaceCore~1documentation~1DotFaceCore~1ValueRange\/title","op":"replace","value":"DOTFValueRange"},{"path":"\/references\/doc:~1~1DotFaceCore~1documentation~1DotFaceCore~1ValueRange\/fragments","value":[{"kind":"identifier","text":"DOTFValueRange"}],"op":"replace"},{"op":"replace","path":"\/references\/doc:~1~1DotFaceCore~1documentation~1DotFaceCore~1HeadPoseAttribute\/title","value":"DOTFHeadPoseAttribute"},{"op":"replace","path":"\/references\/doc:~1~1DotFaceCore~1documentation~1DotFaceCore~1HeadPoseAttribute\/fragments","value":[{"kind":"identifier","text":"DOTFHeadPoseAttribute"}]},{"path":"\/references\/doc:~1~1DotFaceCore~1documentation~1DotFaceCore~1BgraRawImage\/title","op":"replace","value":"DOTBgraRawImage"},{"value":[{"kind":"identifier","text":"DOTBgraRawImage"}],"op":"replace","path":"\/references\/doc:~1~1DotFaceCore~1documentation~1DotFaceCore~1BgraRawImage\/fragments"},{"op":"replace","value":"DOTBgraRawImageFactory","path":"\/references\/doc:~1~1DotFaceCore~1documentation~1DotFaceCore~1BgraRawImageFactory\/title"},{"op":"replace","path":"\/references\/doc:~1~1DotFaceCore~1documentation~1DotFaceCore~1BgraRawImageFactory\/fragments","value":[{"text":"DOTBgraRawImageFactory","kind":"identifier"}]},{"op":"replace","path":"\/references\/doc:~1~1DotFaceCore~1documentation~1DotFaceCore~1MagnifEyeLivenessViewController\/title","value":"DOTFMagnifEyeLivenessViewController"},{"op":"replace","value":[{"kind":"identifier","text":"DOTFMagnifEyeLivenessViewController"}],"path":"\/references\/doc:~1~1DotFaceCore~1documentation~1DotFaceCore~1MagnifEyeLivenessViewController\/fragments"},{"op":"replace","path":"\/references\/doc:~1~1DotFaceCore~1documentation~1DotFaceCore~1EyesExpressionQuery\/title","value":"DOTFEyesExpressionQuery"},{"op":"replace","value":[{"kind":"identifier","text":"DOTFEyesExpressionQuery"}],"path":"\/references\/doc:~1~1DotFaceCore~1documentation~1DotFaceCore~1EyesExpressionQuery\/fragments"},{"op":"replace","value":"DotFaceLibrary","path":"\/references\/doc:~1~1DotFaceCore~1documentation~1DotFaceCore~1DotFaceLibrary\/title"},{"op":"replace","path":"\/references\/doc:~1~1DotFaceCore~1documentation~1DotFaceCore~1DotFaceLibrary\/fragments","value":[{"text":"DotFaceLibrary","kind":"identifier"}]},{"op":"replace","path":"\/references\/doc:~1~1DotFaceCore~1documentation~1DotFaceCore~1DotLibraryId\/title","value":"DotLibraryId"},{"op":"replace","path":"\/references\/doc:~1~1DotFaceCore~1documentation~1DotFaceCore~1DotLibraryId\/fragments","value":[{"kind":"identifier","text":"DotLibraryId"}]},{"path":"\/references\/doc:~1~1DotFaceCore~1documentation~1DotFaceCore~1DotSdk\/title","value":"DotSdk","op":"replace"},{"path":"\/references\/doc:~1~1DotFaceCore~1documentation~1DotFaceCore~1DotSdk\/fragments","value":[{"text":"DotSdk","kind":"identifier"}],"op":"replace"},{"path":"\/references\/doc:~1~1DotFaceCore~1documentation~1DotFaceCore~1ExpressionQuery\/title","op":"replace","value":"DOTFExpressionQuery"},{"value":[{"kind":"identifier","text":"DOTFExpressionQuery"}],"op":"replace","path":"\/references\/doc:~1~1DotFaceCore~1documentation~1DotFaceCore~1ExpressionQuery\/fragments"},{"op":"replace","path":"\/references\/doc:~1~1DotFaceCore~1documentation~1DotFaceCore~1EyeGazeLivenessResult\/title","value":"DOTFEyeGazeLivenessResult"},{"value":[{"text":"DOTFEyeGazeLivenessResult","kind":"identifier"}],"op":"replace","path":"\/references\/doc:~1~1DotFaceCore~1documentation~1DotFaceCore~1EyeGazeLivenessResult\/fragments"},{"value":"DOTFFaceFeature","op":"replace","path":"\/references\/doc:~1~1DotFaceCore~1documentation~1DotFaceCore~1FaceFeature\/title"},{"value":[{"kind":"identifier","text":"DOTFFaceFeature"}],"path":"\/references\/doc:~1~1DotFaceCore~1documentation~1DotFaceCore~1FaceFeature\/fragments","op":"replace"},{"path":"\/references\/doc:~1~1DotFaceCore~1documentation~1DotFaceCore~1EyeGazeLivenessCorner\/title","value":"DOTFEyeGazeLivenessCorner","op":"replace"},{"op":"replace","path":"\/references\/doc:~1~1DotFaceCore~1documentation~1DotFaceCore~1EyeGazeLivenessCorner\/fragments","value":[{"kind":"identifier","text":"DOTFEyeGazeLivenessCorner"}]},{"value":"DOTFFaceMatcher","op":"replace","path":"\/references\/doc:~1~1DotFaceCore~1documentation~1DotFaceCore~1FaceMatcher\/title"},{"path":"\/references\/doc:~1~1DotFaceCore~1documentation~1DotFaceCore~1FaceMatcher\/fragments","value":[{"kind":"identifier","text":"DOTFFaceMatcher"}],"op":"replace"},{"value":"DotFaceModule","op":"replace","path":"\/references\/doc:~1~1DotFaceCore~1documentation~1DotFaceCore~1DotFaceModule\/title"},{"op":"replace","path":"\/references\/doc:~1~1DotFaceCore~1documentation~1DotFaceCore~1DotFaceModule\/fragments","value":[{"kind":"identifier","text":"DotFaceModule"}]},{"value":"DOTCGImageFactory","op":"replace","path":"\/references\/doc:~1~1DotFaceCore~1documentation~1DotFaceCore~1CGImageFactory\/title"},{"value":[{"text":"DOTCGImageFactory","kind":"identifier"}],"op":"replace","path":"\/references\/doc:~1~1DotFaceCore~1documentation~1DotFaceCore~1CGImageFactory\/fragments"},{"path":"\/references\/doc:~1~1DotFaceCore~1documentation~1DotFaceCore~1HeadPose\/title","op":"replace","value":"DOTFHeadPose"},{"path":"\/references\/doc:~1~1DotFaceCore~1documentation~1DotFaceCore~1HeadPose\/fragments","value":[{"text":"DOTFHeadPose","kind":"identifier"}],"op":"replace"},{"value":"DOTFRandomEyeGazeLivenessCornersGenerator","path":"\/references\/doc:~1~1DotFaceCore~1documentation~1DotFaceCore~1RandomEyeGazeLivenessCornersGenerator\/title","op":"replace"},{"op":"replace","value":[{"kind":"identifier","text":"DOTFRandomEyeGazeLivenessCornersGenerator"}],"path":"\/references\/doc:~1~1DotFaceCore~1documentation~1DotFaceCore~1RandomEyeGazeLivenessCornersGenerator\/fragments"},{"op":"replace","value":"DotFaceModuleId","path":"\/references\/doc:~1~1DotFaceCore~1documentation~1DotFaceCore~1DotFaceModuleId\/title"},{"op":"replace","path":"\/references\/doc:~1~1DotFaceCore~1documentation~1DotFaceCore~1DotFaceModuleId\/fragments","value":[{"text":"DotFaceModuleId","kind":"identifier"}]},{"op":"replace","value":"DOTFWrappedEyeGazeLivenessCorner","path":"\/references\/doc:~1~1DotFaceCore~1documentation~1DotFaceCore~1WrappedEyeGazeLivenessCorner\/title"},{"op":"replace","path":"\/references\/doc:~1~1DotFaceCore~1documentation~1DotFaceCore~1WrappedEyeGazeLivenessCorner\/fragments","value":[{"text":"DOTFWrappedEyeGazeLivenessCorner","kind":"identifier"}]},{"path":"\/references\/doc:~1~1DotFaceCore~1documentation~1DotFaceCore~1RectangleDouble\/title","op":"replace","value":"DOTRectangleDouble"},{"value":[{"text":"DOTRectangleDouble","kind":"identifier"}],"op":"replace","path":"\/references\/doc:~1~1DotFaceCore~1documentation~1DotFaceCore~1RectangleDouble\/fragments"},{"value":"DotLibrary","op":"replace","path":"\/references\/doc:~1~1DotFaceCore~1documentation~1DotFaceCore~1DotLibrary\/title"},{"op":"replace","value":[{"text":"DotLibrary","kind":"identifier"}],"path":"\/references\/doc:~1~1DotFaceCore~1documentation~1DotFaceCore~1DotLibrary\/fragments"},{"value":"DOTFFaceAutoCaptureViewController","op":"replace","path":"\/references\/doc:~1~1DotFaceCore~1documentation~1DotFaceCore~1FaceAutoCaptureViewController\/title"},{"op":"replace","path":"\/references\/doc:~1~1DotFaceCore~1documentation~1DotFaceCore~1FaceAutoCaptureViewController\/fragments","value":[{"text":"DOTFFaceAutoCaptureViewController","kind":"identifier"}]},{"op":"replace","path":"\/references\/doc:~1~1DotFaceCore~1documentation~1DotFaceCore~1FaceFeatureWrapper\/title","value":"DOTFFaceFeatureWrapper"},{"op":"replace","path":"\/references\/doc:~1~1DotFaceCore~1documentation~1DotFaceCore~1FaceFeatureWrapper\/fragments","value":[{"kind":"identifier","text":"DOTFFaceFeatureWrapper"}]},{"value":"DOTCaptureMode","op":"replace","path":"\/references\/doc:~1~1DotFaceCore~1documentation~1DotFaceCore~1CaptureMode\/title"},{"op":"replace","value":[{"kind":"identifier","text":"DOTCaptureMode"}],"path":"\/references\/doc:~1~1DotFaceCore~1documentation~1DotFaceCore~1CaptureMode\/fragments"},{"op":"replace","path":"\/references\/doc:~1~1DotFaceCore~1documentation~1DotFaceCore~1CameraPreviewScaleType\/title","value":"DOTCameraPreviewScaleType"},{"value":[{"kind":"identifier","text":"DOTCameraPreviewScaleType"}],"path":"\/references\/doc:~1~1DotFaceCore~1documentation~1DotFaceCore~1CameraPreviewScaleType\/fragments","op":"replace"},{"value":"DOTFEyesExpression","path":"\/references\/doc:~1~1DotFaceCore~1documentation~1DotFaceCore~1EyesExpression\/title","op":"replace"},{"value":[{"text":"DOTFEyesExpression","kind":"identifier"}],"path":"\/references\/doc:~1~1DotFaceCore~1documentation~1DotFaceCore~1EyesExpression\/fragments","op":"replace"},{"op":"replace","value":"DOTFEyeGazeLivenessCornersGenerator","path":"\/references\/doc:~1~1DotFaceCore~1documentation~1DotFaceCore~1EyeGazeLivenessCornersGenerator\/title"},{"op":"replace","path":"\/references\/doc:~1~1DotFaceCore~1documentation~1DotFaceCore~1EyeGazeLivenessCornersGenerator\/fragments","value":[{"text":"DOTFEyeGazeLivenessCornersGenerator","kind":"identifier"}]},{"path":"\/references\/doc:~1~1DotFaceCore~1documentation~1DotFaceCore~1FaceImageQualityQuery\/title","op":"replace","value":"DOTFFaceImageQualityQuery"},{"op":"replace","path":"\/references\/doc:~1~1DotFaceCore~1documentation~1DotFaceCore~1FaceImageQualityQuery\/fragments","value":[{"text":"DOTFFaceImageQualityQuery","kind":"identifier"}]},{"path":"\/references\/doc:~1~1DotFaceCore~1documentation~1DotFaceCore~1LoggerLogLevel\/title","op":"replace","value":"DOTLoggerLogLevel"},{"path":"\/references\/doc:~1~1DotFaceCore~1documentation~1DotFaceCore~1LoggerLogLevel\/fragments","op":"replace","value":[{"kind":"identifier","text":"DOTLoggerLogLevel"}]},{"path":"\/references\/doc:~1~1DotFaceCore~1documentation~1DotFaceCore~1FaceQuality\/title","op":"replace","value":"DOTFFaceQuality"},{"value":[{"kind":"identifier","text":"DOTFFaceQuality"}],"op":"replace","path":"\/references\/doc:~1~1DotFaceCore~1documentation~1DotFaceCore~1FaceQuality\/fragments"},{"value":"DOTWrappedFloat","path":"\/references\/doc:~1~1DotFaceCore~1documentation~1DotFaceCore~1WrappedFloat\/title","op":"replace"},{"op":"replace","path":"\/references\/doc:~1~1DotFaceCore~1documentation~1DotFaceCore~1WrappedFloat\/fragments","value":[{"text":"DOTWrappedFloat","kind":"identifier"}]},{"op":"replace","path":"\/references\/doc:~1~1DotFaceCore~1documentation~1DotFaceCore~1CIImageFactory\/title","value":"DOTCIImageFactory"},{"op":"replace","path":"\/references\/doc:~1~1DotFaceCore~1documentation~1DotFaceCore~1CIImageFactory\/fragments","value":[{"text":"DOTCIImageFactory","kind":"identifier"}]},{"op":"replace","path":"\/references\/doc:~1~1DotFaceCore~1documentation~1DotFaceCore~1FaceAspects\/title","value":"DOTFFaceAspects"},{"op":"replace","path":"\/references\/doc:~1~1DotFaceCore~1documentation~1DotFaceCore~1FaceAspects\/fragments","value":[{"kind":"identifier","text":"DOTFFaceAspects"}]},{"op":"replace","path":"\/references\/doc:~1~1DotFaceCore~1documentation~1DotFaceCore~1SmileLivenessViewController\/title","value":"DOTFSmileLivenessViewController"},{"path":"\/references\/doc:~1~1DotFaceCore~1documentation~1DotFaceCore~1SmileLivenessViewController\/fragments","value":[{"kind":"identifier","text":"DOTFSmileLivenessViewController"}],"op":"replace"},{"value":"DOTFFaceSimpleCaptureViewController","path":"\/references\/doc:~1~1DotFaceCore~1documentation~1DotFaceCore~1FaceSimpleCaptureViewController\/title","op":"replace"},{"path":"\/references\/doc:~1~1DotFaceCore~1documentation~1DotFaceCore~1FaceSimpleCaptureViewController\/fragments","value":[{"text":"DOTFFaceSimpleCaptureViewController","kind":"identifier"}],"op":"replace"},{"path":"\/references\/doc:~1~1DotFaceCore~1documentation~1DotFaceCore~1IntervalFloat\/title","value":"DOTIntervalFloat","op":"replace"},{"value":[{"kind":"identifier","text":"DOTIntervalFloat"}],"op":"replace","path":"\/references\/doc:~1~1DotFaceCore~1documentation~1DotFaceCore~1IntervalFloat\/fragments"},{"path":"\/references\/doc:~1~1DotFaceCore~1documentation~1DotFaceCore~1WearablesQuery\/title","value":"DOTFWearablesQuery","op":"replace"},{"path":"\/references\/doc:~1~1DotFaceCore~1documentation~1DotFaceCore~1WearablesQuery\/fragments","op":"replace","value":[{"text":"DOTFWearablesQuery","kind":"identifier"}]},{"path":"\/references\/doc:~1~1DotFaceCore~1documentation~1DotFaceCore~1FaceDetector\/title","value":"DOTFFaceDetector","op":"replace"},{"op":"replace","path":"\/references\/doc:~1~1DotFaceCore~1documentation~1DotFaceCore~1FaceDetector\/fragments","value":[{"kind":"identifier","text":"DOTFFaceDetector"}]},{"value":"DOTFHeadPoseQuery","path":"\/references\/doc:~1~1DotFaceCore~1documentation~1DotFaceCore~1HeadPoseQuery\/title","op":"replace"},{"op":"replace","value":[{"text":"DOTFHeadPoseQuery","kind":"identifier"}],"path":"\/references\/doc:~1~1DotFaceCore~1documentation~1DotFaceCore~1HeadPoseQuery\/fragments"},{"value":"FaceDetectionQuery","op":"replace","path":"\/references\/doc:~1~1DotFaceCore~1documentation~1DotFaceCore~1FaceDetectionQuery\/title"},{"value":[{"text":"FaceDetectionQuery","kind":"identifier"}],"op":"replace","path":"\/references\/doc:~1~1DotFaceCore~1documentation~1DotFaceCore~1FaceDetectionQuery\/fragments"},{"op":"replace","path":"\/references\/doc:~1~1DotFaceCore~1documentation~1DotFaceCore~1BgrRawImage\/title","value":"DOTBgrRawImage"},{"op":"replace","value":[{"text":"DOTBgrRawImage","kind":"identifier"}],"path":"\/references\/doc:~1~1DotFaceCore~1documentation~1DotFaceCore~1BgrRawImage\/fragments"},{"path":"\/references\/doc:~1~1DotFaceCore~1documentation~1DotFaceCore~1Localization\/title","op":"replace","value":"DOTFLocalization"},{"value":[{"text":"DOTFLocalization","kind":"identifier"}],"path":"\/references\/doc:~1~1DotFaceCore~1documentation~1DotFaceCore~1Localization\/fragments","op":"replace"},{"op":"replace","value":"DOTTiltAngles","path":"\/references\/doc:~1~1DotFaceCore~1documentation~1DotFaceCore~1TiltAngles\/title"},{"value":[{"text":"DOTTiltAngles","kind":"identifier"}],"path":"\/references\/doc:~1~1DotFaceCore~1documentation~1DotFaceCore~1TiltAngles\/fragments","op":"replace"},{"op":"replace","path":"\/references\/doc:~1~1DotFaceCore~1documentation~1DotFaceCore~1DotSdkLicenseProxyProtocol\/title","value":"DotSdkLicenseProxyProtocol"},{"value":[{"text":"DotSdkLicenseProxyProtocol","kind":"identifier"}],"path":"\/references\/doc:~1~1DotFaceCore~1documentation~1DotFaceCore~1DotSdkLicenseProxyProtocol\/fragments","op":"replace"},{"value":"DOTBgrRawImageFactory","path":"\/references\/doc:~1~1DotFaceCore~1documentation~1DotFaceCore~1BgrRawImageFactory\/title","op":"replace"},{"value":[{"kind":"identifier","text":"DOTBgrRawImageFactory"}],"op":"replace","path":"\/references\/doc:~1~1DotFaceCore~1documentation~1DotFaceCore~1BgrRawImageFactory\/fragments"},{"value":"DOTFTemplateMatcher","op":"replace","path":"\/references\/doc:~1~1DotFaceCore~1documentation~1DotFaceCore~1TemplateMatcher\/title"},{"value":[{"text":"DOTFTemplateMatcher","kind":"identifier"}],"op":"replace","path":"\/references\/doc:~1~1DotFaceCore~1documentation~1DotFaceCore~1TemplateMatcher\/fragments"},{"value":"DOTFFaceFeaturePoint","op":"replace","path":"\/references\/doc:~1~1DotFaceCore~1documentation~1DotFaceCore~1FaceFeaturePoint\/title"},{"value":[{"kind":"identifier","text":"DOTFFaceFeaturePoint"}],"op":"replace","path":"\/references\/doc:~1~1DotFaceCore~1documentation~1DotFaceCore~1FaceFeaturePoint\/fragments"},{"path":"\/references\/doc:~1~1DotFaceCore~1documentation~1DotFaceCore~1EyeGazeLivenessViewController\/title","value":"DOTFEyeGazeLivenessViewController","op":"replace"},{"path":"\/references\/doc:~1~1DotFaceCore~1documentation~1DotFaceCore~1EyeGazeLivenessViewController\/fragments","op":"replace","value":[{"kind":"identifier","text":"DOTFEyeGazeLivenessViewController"}]},{"op":"replace","path":"\/references\/doc:~1~1DotFaceCore~1documentation~1DotFaceCore~1WrappedDouble\/title","value":"DOTWrappedDouble"},{"op":"replace","path":"\/references\/doc:~1~1DotFaceCore~1documentation~1DotFaceCore~1WrappedDouble\/fragments","value":[{"text":"DOTWrappedDouble","kind":"identifier"}]},{"path":"\/references\/doc:~1~1DotFaceCore~1documentation~1DotFaceCore~1DotSdkConfiguration\/title","op":"replace","value":"DotSdkConfiguration"},{"value":[{"kind":"identifier","text":"DotSdkConfiguration"}],"op":"replace","path":"\/references\/doc:~1~1DotFaceCore~1documentation~1DotFaceCore~1DotSdkConfiguration\/fragments"}]}]}