{"sections":[],"schemaVersion":{"patch":0,"major":0,"minor":3},"hierarchy":{"paths":[["doc:\/\/DotFaceCore\/documentation\/DotFaceCore","doc:\/\/DotFaceCore\/documentation\/DotFaceCore\/DOTFFaceAutoCaptureConfiguration"]]},"identifier":{"url":"doc:\/\/DotFaceCore\/documentation\/DotFaceCore\/DOTFFaceAutoCaptureConfiguration\/initWithSessionToken:qualityAttributeThresholds:minValidFramesInRowToStartCandidateSelection:candidateSelectionDurationMillis:query:faceSizeRatioInterval:captureMode:isPlaceholderVisible:isDetectionLayerVisible:isTorchEnabled:isVideoCaptureEnabled:cameraFacing:cameraPreviewScaleType:isCameraPreviewVisible:error:","interfaceLanguage":"occ"},"primaryContentSections":[{"kind":"declarations","declarations":[{"tokens":[{"kind":"text","text":"- ("},{"kind":"keyword","text":"id"},{"text":") ","kind":"text"},{"kind":"identifier","text":"initWithSessionToken:"},{"text":"(","kind":"text"},{"preciseIdentifier":"c:objc(cs)NSString","text":"NSString","kind":"typeIdentifier"},{"text":" *) ","kind":"text"},{"kind":"internalParam","text":"sessionToken"},{"text":" ","kind":"text"},{"kind":"identifier","text":"qualityAttributeThresholds:"},{"text":"(","kind":"text"},{"preciseIdentifier":"c:@M@DotFaceCore@objc(cs)DOTFQualityAttributeThresholds","identifier":"doc:\/\/DotFaceCore\/documentation\/DotFaceCore\/DOTFQualityAttributeThresholds","kind":"typeIdentifier","text":"DOTFQualityAttributeThresholds"},{"text":" *) ","kind":"text"},{"text":"qualityAttributeThresholds","kind":"internalParam"},{"kind":"text","text":" "},{"kind":"identifier","text":"minValidFramesInRowToStartCandidateSelection:"},{"kind":"text","text":"("},{"kind":"typeIdentifier","preciseIdentifier":"c:@T@NSInteger","text":"NSInteger"},{"kind":"text","text":") "},{"kind":"internalParam","text":"minValidFramesInRowToStartCandidateSelection"},{"kind":"text","text":" "},{"text":"candidateSelectionDurationMillis:","kind":"identifier"},{"text":"(","kind":"text"},{"kind":"typeIdentifier","preciseIdentifier":"c:@T@NSInteger","text":"NSInteger"},{"kind":"text","text":") "},{"kind":"internalParam","text":"candidateSelectionDurationMillis"},{"kind":"text","text":" "},{"text":"query:","kind":"identifier"},{"text":"(","kind":"text"},{"text":"FaceDetectionQuery","preciseIdentifier":"c:@M@DotFaceCore@objc(cs)FaceDetectionQuery","identifier":"doc:\/\/DotFaceCore\/documentation\/DotFaceCore\/FaceDetectionQuery","kind":"typeIdentifier"},{"text":" *) ","kind":"text"},{"text":"query","kind":"internalParam"},{"text":" ","kind":"text"},{"text":"faceSizeRatioInterval:","kind":"identifier"},{"text":"(","kind":"text"},{"preciseIdentifier":"c:@M@DotCore@objc(cs)DOTIntervalDouble","identifier":"doc:\/\/DotFaceCore\/documentation\/DotFaceCore\/IntervalDouble","kind":"typeIdentifier","text":"DOTIntervalDouble"},{"text":" *) ","kind":"text"},{"text":"faceSizeRatioInterval","kind":"internalParam"},{"text":" ","kind":"text"},{"text":"captureMode:","kind":"identifier"},{"kind":"text","text":"("},{"text":"enum","kind":"keyword"},{"kind":"text","text":" "},{"preciseIdentifier":"c:@M@DotCapture@E@DOTCaptureMode","text":"DOTCaptureMode","identifier":"doc:\/\/DotFaceCore\/documentation\/DotFaceCore\/CaptureMode","kind":"typeIdentifier"},{"text":") ","kind":"text"},{"text":"captureMode","kind":"internalParam"},{"kind":"text","text":" "},{"text":"isPlaceholderVisible:","kind":"identifier"},{"text":"(","kind":"text"},{"text":"BOOL","kind":"typeIdentifier","preciseIdentifier":"c:@T@BOOL"},{"text":") ","kind":"text"},{"text":"isPlaceholderVisible","kind":"internalParam"},{"text":" ","kind":"text"},{"kind":"identifier","text":"isDetectionLayerVisible:"},{"kind":"text","text":"("},{"text":"BOOL","kind":"typeIdentifier","preciseIdentifier":"c:@T@BOOL"},{"kind":"text","text":") "},{"text":"isDetectionLayerVisible","kind":"internalParam"},{"text":" ","kind":"text"},{"text":"isTorchEnabled:","kind":"identifier"},{"kind":"text","text":"("},{"text":"BOOL","preciseIdentifier":"c:@T@BOOL","kind":"typeIdentifier"},{"kind":"text","text":") "},{"text":"isTorchEnabled","kind":"internalParam"},{"kind":"text","text":" "},{"kind":"identifier","text":"isVideoCaptureEnabled:"},{"text":"(","kind":"text"},{"preciseIdentifier":"c:@T@BOOL","text":"BOOL","kind":"typeIdentifier"},{"kind":"text","text":") "},{"kind":"internalParam","text":"isVideoCaptureEnabled"},{"text":" ","kind":"text"},{"kind":"identifier","text":"cameraFacing:"},{"kind":"text","text":"("},{"kind":"keyword","text":"enum"},{"text":" ","kind":"text"},{"kind":"typeIdentifier","identifier":"doc:\/\/DotFaceCore\/documentation\/DotFaceCore\/CameraFacing","text":"DOTCameraFacing","preciseIdentifier":"c:@M@DotCamera@E@DOTCameraFacing"},{"kind":"text","text":") "},{"kind":"internalParam","text":"cameraFacing"},{"kind":"text","text":" "},{"text":"cameraPreviewScaleType:","kind":"identifier"},{"text":"(","kind":"text"},{"text":"enum","kind":"keyword"},{"text":" ","kind":"text"},{"identifier":"doc:\/\/DotFaceCore\/documentation\/DotFaceCore\/CameraPreviewScaleType","preciseIdentifier":"c:@M@DotCamera@E@DOTCameraPreviewScaleType","text":"DOTCameraPreviewScaleType","kind":"typeIdentifier"},{"text":") ","kind":"text"},{"kind":"internalParam","text":"cameraPreviewScaleType"},{"kind":"text","text":" "},{"text":"isCameraPreviewVisible:","kind":"identifier"},{"text":"(","kind":"text"},{"kind":"typeIdentifier","preciseIdentifier":"c:@T@BOOL","text":"BOOL"},{"text":") ","kind":"text"},{"kind":"internalParam","text":"isCameraPreviewVisible"},{"kind":"text","text":" "},{"text":"error:","kind":"identifier"},{"text":"(","kind":"text"},{"kind":"typeIdentifier","preciseIdentifier":"c:objc(cs)NSError","text":"NSError"},{"text":" * *) ","kind":"text"},{"text":"error","kind":"internalParam"},{"kind":"text","text":";"}],"platforms":["iOS"],"languages":["occ"]}]}],"abstract":[{"type":"text","text":"Create the face auto capture configuration."}],"variants":[{"traits":[{"interfaceLanguage":"occ"}],"paths":["\/documentation\/dotfacecore\/dotffaceautocaptureconfiguration\/initwithsessiontoken:qualityattributethresholds:minvalidframesinrowtostartcandidateselection:candidateselectiondurationmillis:query:facesizeratiointerval:capturemode:isplaceholdervisible:isdetectionlayervisible:istorchenabled:isvideocapture-6o7v8"]}],"metadata":{"role":"symbol","symbolKind":"method","externalID":"c:@M@DotFaceCore@objc(cs)DOTFFaceAutoCaptureConfiguration(im)initWithSessionToken:qualityAttributeThresholds:minValidFramesInRowToStartCandidateSelection:candidateSelectionDurationMillis:query:faceSizeRatioInterval:captureMode:isPlaceholderVisible:isDetectionLayerVisible:isTorchEnabled:isVideoCaptureEnabled:cameraFacing:cameraPreviewScaleType:isCameraPreviewVisible:error:","fragments":[{"text":"- ","kind":"text"},{"text":"initWithSessionToken:qualityAttributeThresholds:minValidFramesInRowToStartCandidateSelection:candidateSelectionDurationMillis:query:faceSizeRatioInterval:captureMode:isPlaceholderVisible:isDetectionLayerVisible:isTorchEnabled:isVideoCaptureEnabled:cameraFacing:cameraPreviewScaleType:isCameraPreviewVisible:error:","kind":"identifier"}],"title":"initWithSessionToken:qualityAttributeThresholds:minValidFramesInRowToStartCandidateSelection:candidateSelectionDurationMillis:query:faceSizeRatioInterval:captureMode:isPlaceholderVisible:isDetectionLayerVisible:isTorchEnabled:isVideoCaptureEnabled:cameraFacing:cameraPreviewScaleType:isCameraPreviewVisible:error:","roleHeading":"Instance Method","navigatorTitle":[{"kind":"identifier","text":"initWithSessionToken:qualityAttributeThresholds:minValidFramesInRowToStartCandidateSelection:candidateSelectionDurationMillis:query:faceSizeRatioInterval:captureMode:isPlaceholderVisible:isDetectionLayerVisible:isTorchEnabled:isVideoCaptureEnabled:cameraFacing:cameraPreviewScaleType:isCameraPreviewVisible:error:"}],"modules":[{"name":"DotFaceCore"}]},"kind":"symbol","references":{"doc://DotFaceCore/documentation/DotFaceCore":{"title":"DotFaceCore","kind":"symbol","url":"\/documentation\/dotfacecore","abstract":[{"text":"version: 8.17.0","type":"text"}],"type":"topic","identifier":"doc:\/\/DotFaceCore\/documentation\/DotFaceCore","role":"collection"},"doc://DotFaceCore/documentation/DotFaceCore/FaceDetectionQuery":{"kind":"symbol","url":"\/documentation\/dotfacecore\/facedetectionquery","role":"symbol","fragments":[{"text":"class","kind":"keyword"},{"text":" ","kind":"text"},{"text":"FaceDetectionQuery","kind":"identifier"}],"navigatorTitle":[{"text":"FaceDetectionQuery","kind":"identifier"}],"abstract":[{"type":"text","text":"Face detection query. It allows additional processing beyond basic face detection."}],"title":"FaceDetectionQuery","identifier":"doc:\/\/DotFaceCore\/documentation\/DotFaceCore\/FaceDetectionQuery","type":"topic"},"doc://DotFaceCore/documentation/DotFaceCore/DOTFFaceAutoCaptureConfiguration/initWithSessionToken:qualityAttributeThresholds:minValidFramesInRowToStartCandidateSelection:candidateSelectionDurationMillis:query:faceSizeRatioInterval:captureMode:isPlaceholderVisible:isDetectionLayerVisible:isTorchEnabled:isVideoCaptureEnabled:cameraFacing:cameraPreviewScaleType:isCameraPreviewVisible:error:":{"type":"topic","navigatorTitle":[{"kind":"identifier","text":"initWithSessionToken:qualityAttributeThresholds:minValidFramesInRowToStartCandidateSelection:candidateSelectionDurationMillis:query:faceSizeRatioInterval:captureMode:isPlaceholderVisible:isDetectionLayerVisible:isTorchEnabled:isVideoCaptureEnabled:cameraFacing:cameraPreviewScaleType:isCameraPreviewVisible:error:"}],"abstract":[{"text":"Create the face auto capture configuration.","type":"text"}],"title":"initWithSessionToken:qualityAttributeThresholds:minValidFramesInRowToStartCandidateSelection:candidateSelectionDurationMillis:query:faceSizeRatioInterval:captureMode:isPlaceholderVisible:isDetectionLayerVisible:isTorchEnabled:isVideoCaptureEnabled:cameraFacing:cameraPreviewScaleType:isCameraPreviewVisible:error:","fragments":[{"kind":"text","text":"- "},{"text":"initWithSessionToken:qualityAttributeThresholds:minValidFramesInRowToStartCandidateSelection:candidateSelectionDurationMillis:query:faceSizeRatioInterval:captureMode:isPlaceholderVisible:isDetectionLayerVisible:isTorchEnabled:isVideoCaptureEnabled:cameraFacing:cameraPreviewScaleType:isCameraPreviewVisible:error:","kind":"identifier"}],"kind":"symbol","role":"symbol","identifier":"doc:\/\/DotFaceCore\/documentation\/DotFaceCore\/DOTFFaceAutoCaptureConfiguration\/initWithSessionToken:qualityAttributeThresholds:minValidFramesInRowToStartCandidateSelection:candidateSelectionDurationMillis:query:faceSizeRatioInterval:captureMode:isPlaceholderVisible:isDetectionLayerVisible:isTorchEnabled:isVideoCaptureEnabled:cameraFacing:cameraPreviewScaleType:isCameraPreviewVisible:error:","url":"\/documentation\/dotfacecore\/dotffaceautocaptureconfiguration\/initwithsessiontoken:qualityattributethresholds:minvalidframesinrowtostartcandidateselection:candidateselectiondurationmillis:query:facesizeratiointerval:capturemode:isplaceholdervisible:isdetectionlayervisible:istorchenabled:isvideocapture-6o7v8"},"doc://DotFaceCore/documentation/DotFaceCore/CameraFacing":{"identifier":"doc:\/\/DotFaceCore\/documentation\/DotFaceCore\/CameraFacing","title":"CameraFacing","fragments":[{"text":"enum","kind":"keyword"},{"kind":"text","text":" "},{"text":"CameraFacing","kind":"identifier"}],"abstract":[{"text":"Facing of the camera on the device.","type":"text"}],"url":"\/documentation\/dotfacecore\/camerafacing","navigatorTitle":[{"text":"CameraFacing","kind":"identifier"}],"kind":"symbol","role":"symbol","type":"topic"},"doc://DotFaceCore/documentation/DotFaceCore/DOTFFaceAutoCaptureConfiguration":{"kind":"symbol","url":"\/documentation\/dotfacecore\/dotffaceautocaptureconfiguration","role":"symbol","title":"DOTFFaceAutoCaptureConfiguration","identifier":"doc:\/\/DotFaceCore\/documentation\/DotFaceCore\/DOTFFaceAutoCaptureConfiguration","fragments":[{"kind":"identifier","text":"DOTFFaceAutoCaptureConfiguration"}],"type":"topic","abstract":[{"type":"text","text":"Configuration options for the face auto capture process."}]},"doc://DotFaceCore/documentation/DotFaceCore/IntervalDouble":{"fragments":[{"text":"class","kind":"keyword"},{"text":" ","kind":"text"},{"kind":"identifier","text":"IntervalDouble"}],"abstract":[{"type":"text","text":"Representation of closed interval with value type "},{"code":"Double","type":"codeVoice"},{"text":".","type":"text"},{"text":" ","type":"text"},{"type":"text","text":"The "},{"type":"codeVoice","code":"max"},{"type":"text","text":" must be greater than the "},{"type":"codeVoice","code":"min"},{"type":"text","text":"."}],"navigatorTitle":[{"text":"IntervalDouble","kind":"identifier"}],"url":"\/documentation\/dotfacecore\/intervaldouble","identifier":"doc:\/\/DotFaceCore\/documentation\/DotFaceCore\/IntervalDouble","title":"IntervalDouble","role":"symbol","kind":"symbol","type":"topic"},"doc://DotFaceCore/documentation/DotFaceCore/CameraPreviewScaleType":{"type":"topic","navigatorTitle":[{"text":"CameraPreviewScaleType","kind":"identifier"}],"abstract":[{"type":"text","text":"Indicates how the layer displays video frames."}],"role":"symbol","url":"\/documentation\/dotfacecore\/camerapreviewscaletype","fragments":[{"text":"enum","kind":"keyword"},{"kind":"text","text":" "},{"kind":"identifier","text":"CameraPreviewScaleType"}],"identifier":"doc:\/\/DotFaceCore\/documentation\/DotFaceCore\/CameraPreviewScaleType","title":"CameraPreviewScaleType","kind":"symbol"},"doc://DotFaceCore/documentation/DotFaceCore/DOTFQualityAttributeThresholds":{"type":"topic","identifier":"doc:\/\/DotFaceCore\/documentation\/DotFaceCore\/DOTFQualityAttributeThresholds","fragments":[{"text":"DOTFQualityAttributeThresholds","kind":"identifier"}],"role":"symbol","url":"\/documentation\/dotfacecore\/dotfqualityattributethresholds","kind":"symbol","abstract":[{"type":"text","text":"Configure thresholds for the quality attributes of the face auto capture result."},{"type":"text","text":" "},{"text":"If the threshold property is set to nil, the corresponding quality attribute will not be validated.","type":"text"}],"title":"DOTFQualityAttributeThresholds"},"doc://DotFaceCore/documentation/DotFaceCore/CaptureMode":{"fragments":[{"kind":"keyword","text":"enum"},{"kind":"text","text":" "},{"kind":"identifier","text":"CaptureMode"}],"role":"symbol","title":"CaptureMode","abstract":[{"type":"text","text":"Capture mode."}],"identifier":"doc:\/\/DotFaceCore\/documentation\/DotFaceCore\/CaptureMode","url":"\/documentation\/dotfacecore\/capturemode","type":"topic","kind":"symbol","navigatorTitle":[{"kind":"identifier","text":"CaptureMode"}]}},"variantOverrides":[{"traits":[{"interfaceLanguage":"occ"}],"patch":[{"value":"FaceDetectionQuery","op":"replace","path":"\/references\/doc:~1~1DotFaceCore~1documentation~1DotFaceCore~1FaceDetectionQuery\/title"},{"path":"\/references\/doc:~1~1DotFaceCore~1documentation~1DotFaceCore~1FaceDetectionQuery\/fragments","op":"replace","value":[{"kind":"identifier","text":"FaceDetectionQuery"}]},{"value":"DOTCameraFacing","path":"\/references\/doc:~1~1DotFaceCore~1documentation~1DotFaceCore~1CameraFacing\/title","op":"replace"},{"op":"replace","value":[{"kind":"identifier","text":"DOTCameraFacing"}],"path":"\/references\/doc:~1~1DotFaceCore~1documentation~1DotFaceCore~1CameraFacing\/fragments"},{"op":"replace","path":"\/references\/doc:~1~1DotFaceCore~1documentation~1DotFaceCore~1IntervalDouble\/title","value":"DOTIntervalDouble"},{"op":"replace","value":[{"text":"DOTIntervalDouble","kind":"identifier"}],"path":"\/references\/doc:~1~1DotFaceCore~1documentation~1DotFaceCore~1IntervalDouble\/fragments"},{"path":"\/references\/doc:~1~1DotFaceCore~1documentation~1DotFaceCore~1CameraPreviewScaleType\/title","op":"replace","value":"DOTCameraPreviewScaleType"},{"op":"replace","value":[{"text":"DOTCameraPreviewScaleType","kind":"identifier"}],"path":"\/references\/doc:~1~1DotFaceCore~1documentation~1DotFaceCore~1CameraPreviewScaleType\/fragments"},{"path":"\/references\/doc:~1~1DotFaceCore~1documentation~1DotFaceCore~1CaptureMode\/title","value":"DOTCaptureMode","op":"replace"},{"value":[{"kind":"identifier","text":"DOTCaptureMode"}],"path":"\/references\/doc:~1~1DotFaceCore~1documentation~1DotFaceCore~1CaptureMode\/fragments","op":"replace"}]}]}